{"bodies":[{"childs":[{"color":"eeeeee","controller":{"containers":null,"controllers":[{"id":2347}],"id":2350,"joints":null},"pos":{"x":7,"y":11,"z":3},"shapeId":"1742f96c-e3b7-408f-8291-06a125e87355","xaxis":2,"zaxis":-3},{"color":"222222","controller":{"active":false,"controllers":[{"id":2343},{"id":2341}],"id":2349,"joints":null,"mode":0},"pos":{"x":7,"y":11,"z":4},"shapeId":"9f0f56e8-2c31-4d83-996c-d00a9b296c3f","xaxis":2,"zaxis":-3},{"color":"7eeded","controller":{"containers":null,"controllers":[{"id":2347},{"id":2341}],"data":"gExVQQAAAAEFBQDQAgAAAAKAc3RhdGUIAA","id":2348,"joints":null},"pos":{"x":7,"y":12,"z":9},"shapeId":"bbd2a902-de99-459e-89cd-3c84de790775","xaxis":-2,"zaxis":3},{"color":"df7f01","controller":{"active":false,"controllers":[{"id":2346}],"id":2347,"joints":null,"mode":2},"pos":{"x":7,"y":12,"z":8},"shapeId":"9f0f56e8-2c31-4d83-996c-d00a9b296c3f","xaxis":-2,"zaxis":3},{"color":"d02525","controller":{"active":false,"controllers":[{"id":2348}],"id":2346,"joints":null,"mode":0},"pos":{"x":7,"y":12,"z":7},"shapeId":"9f0f56e8-2c31-4d83-996c-d00a9b296c3f","xaxis":-2,"zaxis":3},{"color":"0a3ee2","controller":{"active":false,"controllers":[{"id":2346}],"id":2345,"joints":null,"mode":0},"pos":{"x":7,"y":12,"z":6},"shapeId":"9f0f56e8-2c31-4d83-996c-d00a9b296c3f","xaxis":-2,"zaxis":3},{"color":"f06767","controller":{"containers":null,"controllers":[{"id":2343}],"id":2344,"joints":null},"pos":{"x":8,"y":11,"z":6},"shapeId":"1742f96c-e3b7-408f-8291-06a125e87355","xaxis":2,"zaxis":-1},{"color":"f06767","controller":{"active":false,"controllers":[{"id":2345}],"id":2343,"joints":null,"mode":0},"pos":{"x":7,"y":11,"z":5},"shapeId":"9f0f56e8-2c31-4d83-996c-d00a9b296c3f","xaxis":2,"zaxis":-3},{"color":"eeaf5c","controller":{"containers":null,"controllers":[{"id":2341}],"id":2342,"joints":null},"pos":{"x":7,"y":12,"z":10},"shapeId":"1742f96c-e3b7-408f-8291-06a125e87355","xaxis":-2,"zaxis":3},{"color":"35086c","controller":{"active":false,"controllers":[{"id":2340}],"id":2341,"joints":null,"mode":0},"pos":{"x":7,"y":12,"z":11},"shapeId":"9f0f56e8-2c31-4d83-996c-d00a9b296c3f","xaxis":-2,"zaxis":3},{"color":"7eeded","controller":{"containers":null,"controllers":null,"id":2340,"joints":null},"pos":{"x":7,"y":12,"z":12},"shapeId":"b66bf85d-5bee-4461-bee3-b83f371faf04","xaxis":-2,"zaxis":3},{"color":"eeeeee","controller":{"containers":null,"controllers":[{"id":2331}],"id":2339,"joints":null},"pos":{"x":7,"y":12,"z":3},"shapeId":"1742f96c-e3b7-408f-8291-06a125e87355","xaxis":2,"zaxis":-3},{"color":"7eeded","controller":{"containers":null,"controllers":null,"id":2338,"joints":null},"pos":{"x":7,"y":13,"z":12},"shapeId":"b66bf85d-5bee-4461-bee3-b83f371faf04","xaxis":-2,"zaxis":3},{"color":"35086c","controller":{"active":false,"controllers":[{"id":2338}],"id":2337,"joints":null,"mode":0},"pos":{"x":7,"y":13,"z":11},"shapeId":"9f0f56e8-2c31-4d83-996c-d00a9b296c3f","xaxis":-2,"zaxis":3},{"color":"eeaf5c","controller":{"containers":null,"controllers":[{"id":2337}],"id":2336,"joints":null},"pos":{"x":7,"y":13,"z":10},"shapeId":"1742f96c-e3b7-408f-8291-06a125e87355","xaxis":-2,"zaxis":3},{"color":"f06767","controller":{"active":false,"controllers":[{"id":2333}],"id":2335,"joints":null,"mode":0},"pos":{"x":7,"y":12,"z":5},"shapeId":"9f0f56e8-2c31-4d83-996c-d00a9b296c3f","xaxis":2,"zaxis":-3},{"color":"f06767","controller":{"containers":null,"controllers":[{"id":2335}],"id":2334,"joints":null},"pos":{"x":8,"y":12,"z":6},"shapeId":"1742f96c-e3b7-408f-8291-06a125e87355","xaxis":2,"zaxis":-1},{"color":"0a3ee2","controller":{"active":false,"controllers":[{"id":2332}],"id":2333,"joints":null,"mode":0},"pos":{"x":7,"y":13,"z":6},"shapeId":"9f0f56e8-2c31-4d83-996c-d00a9b296c3f","xaxis":-2,"zaxis":3},{"color":"d02525","controller":{"active":false,"controllers":[{"id":2330}],"id":2332,"joints":null,"mode":0},"pos":{"x":7,"y":13,"z":7},"shapeId":"9f0f56e8-2c31-4d83-996c-d00a9b296c3f","xaxis":-2,"zaxis":3},{"color":"df7f01","controller":{"active":false,"controllers":[{"id":2332}],"id":2331,"joints":null,"mode":2},"pos":{"x":7,"y":13,"z":8},"shapeId":"9f0f56e8-2c31-4d83-996c-d00a9b296c3f","xaxis":-2,"zaxis":3},{"color":"7eeded","controller":{"containers":null,"controllers":[{"id":2331},{"id":2337}],"data":"gExVQQAAAAEFBQDQAgAAAAKAc3RhdGUIAA","id":2330,"joints":null},"pos":{"x":7,"y":13,"z":9},"shapeId":"bbd2a902-de99-459e-89cd-3c84de790775","xaxis":-2,"zaxis":3},{"color":"222222","controller":{"active":false,"controllers":[{"id":2335},{"id":2337}],"id":2329,"joints":null,"mode":0},"pos":{"x":7,"y":12,"z":4},"shapeId":"9f0f56e8-2c31-4d83-996c-d00a9b296c3f","xaxis":2,"zaxis":-3},{"color":"eeeeee","controller":{"containers":null,"controllers":[{"id":2320}],"id":2328,"joints":null},"pos":{"x":7,"y":10,"z":3},"shapeId":"1742f96c-e3b7-408f-8291-06a125e87355","xaxis":2,"zaxis":-3},{"color":"7eeded","controller":{"containers":null,"controllers":null,"id":2327,"joints":null},"pos":{"x":7,"y":11,"z":12},"shapeId":"b66bf85d-5bee-4461-bee3-b83f371faf04","xaxis":-2,"zaxis":3},{"color":"35086c","controller":{"active":false,"controllers":[{"id":2327}],"id":2326,"joints":null,"mode":0},"pos":{"x":7,"y":11,"z":11},"shapeId":"9f0f56e8-2c31-4d83-996c-d00a9b296c3f","xaxis":-2,"zaxis":3},{"color":"eeaf5c","controller":{"containers":null,"controllers":[{"id":2326}],"id":2325,"joints":null},"pos":{"x":7,"y":11,"z":10},"shapeId":"1742f96c-e3b7-408f-8291-06a125e87355","xaxis":-2,"zaxis":3},{"color":"f06767","controller":{"active":false,"controllers":[{"id":2322}],"id":2324,"joints":null,"mode":0},"pos":{"x":7,"y":10,"z":5},"shapeId":"9f0f56e8-2c31-4d83-996c-d00a9b296c3f","xaxis":2,"zaxis":-3},{"color":"f06767","controller":{"containers":null,"controllers":[{"id":2324}],"id":2323,"joints":null},"pos":{"x":8,"y":10,"z":6},"shapeId":"1742f96c-e3b7-408f-8291-06a125e87355","xaxis":2,"zaxis":-1},{"color":"0a3ee2","controller":{"active":false,"controllers":[{"id":2321}],"id":2322,"joints":null,"mode":0},"pos":{"x":7,"y":11,"z":6},"shapeId":"9f0f56e8-2c31-4d83-996c-d00a9b296c3f","xaxis":-2,"zaxis":3},{"color":"d02525","controller":{"active":false,"controllers":[{"id":2319}],"id":2321,"joints":null,"mode":0},"pos":{"x":7,"y":11,"z":7},"shapeId":"9f0f56e8-2c31-4d83-996c-d00a9b296c3f","xaxis":-2,"zaxis":3},{"color":"df7f01","controller":{"active":false,"controllers":[{"id":2321}],"id":2320,"joints":null,"mode":2},"pos":{"x":7,"y":11,"z":8},"shapeId":"9f0f56e8-2c31-4d83-996c-d00a9b296c3f","xaxis":-2,"zaxis":3},{"color":"7eeded","controller":{"containers":null,"controllers":[{"id":2320},{"id":2326}],"data":"gExVQQAAAAEFBQDQAgAAAAKAc3RhdGUIAA","id":2319,"joints":null},"pos":{"x":7,"y":11,"z":9},"shapeId":"bbd2a902-de99-459e-89cd-3c84de790775","xaxis":-2,"zaxis":3},{"color":"222222","controller":{"active":false,"controllers":[{"id":2324},{"id":2326}],"id":2318,"joints":null,"mode":0},"pos":{"x":7,"y":10,"z":4},"shapeId":"9f0f56e8-2c31-4d83-996c-d00a9b296c3f","xaxis":2,"zaxis":-3},{"color":"eeeeee","controller":{"containers":null,"controllers":[{"id":2309}],"id":2317,"joints":null},"pos":{"x":7,"y":9,"z":3},"shapeId":"1742f96c-e3b7-408f-8291-06a125e87355","xaxis":2,"zaxis":-3},{"color":"7eeded","controller":{"containers":null,"controllers":null,"id":2316,"joints":null},"pos":{"x":7,"y":10,"z":12},"shapeId":"b66bf85d-5bee-4461-bee3-b83f371faf04","xaxis":-2,"zaxis":3},{"color":"35086c","controller":{"active":false,"controllers":[{"id":2316}],"id":2315,"joints":null,"mode":0},"pos":{"x":7,"y":10,"z":11},"shapeId":"9f0f56e8-2c31-4d83-996c-d00a9b296c3f","xaxis":-2,"zaxis":3},{"color":"eeaf5c","controller":{"containers":null,"controllers":[{"id":2315}],"id":2314,"joints":null},"pos":{"x":7,"y":10,"z":10},"shapeId":"1742f96c-e3b7-408f-8291-06a125e87355","xaxis":-2,"zaxis":3},{"color":"f06767","controller":{"active":false,"controllers":[{"id":2311}],"id":2313,"joints":null,"mode":0},"pos":{"x":7,"y":9,"z":5},"shapeId":"9f0f56e8-2c31-4d83-996c-d00a9b296c3f","xaxis":2,"zaxis":-3},{"color":"f06767","controller":{"containers":null,"controllers":[{"id":2313}],"id":2312,"joints":null},"pos":{"x":8,"y":9,"z":6},"shapeId":"1742f96c-e3b7-408f-8291-06a125e87355","xaxis":2,"zaxis":-1},{"color":"0a3ee2","controller":{"active":false,"controllers":[{"id":2310}],"id":2311,"joints":null,"mode":0},"pos":{"x":7,"y":10,"z":6},"shapeId":"9f0f56e8-2c31-4d83-996c-d00a9b296c3f","xaxis":-2,"zaxis":3},{"color":"d02525","controller":{"active":false,"controllers":[{"id":2308}],"id":2310,"joints":null,"mode":0},"pos":{"x":7,"y":10,"z":7},"shapeId":"9f0f56e8-2c31-4d83-996c-d00a9b296c3f","xaxis":-2,"zaxis":3},{"color":"df7f01","controller":{"active":false,"controllers":[{"id":2310}],"id":2309,"joints":null,"mode":2},"pos":{"x":7,"y":10,"z":8},"shapeId":"9f0f56e8-2c31-4d83-996c-d00a9b296c3f","xaxis":-2,"zaxis":3},{"color":"7eeded","controller":{"containers":null,"controllers":[{"id":2309},{"id":2315}],"data":"gExVQQAAAAEFBQDQAgAAAAKAc3RhdGUIAA","id":2308,"joints":null},"pos":{"x":7,"y":10,"z":9},"shapeId":"bbd2a902-de99-459e-89cd-3c84de790775","xaxis":-2,"zaxis":3},{"color":"222222","controller":{"active":false,"controllers":[{"id":2313},{"id":2315}],"id":2307,"joints":null,"mode":0},"pos":{"x":7,"y":9,"z":4},"shapeId":"9f0f56e8-2c31-4d83-996c-d00a9b296c3f","xaxis":2,"zaxis":-3},{"color":"eeeeee","controller":{"containers":null,"controllers":[{"id":2298}],"id":2306,"joints":null},"pos":{"x":7,"y":8,"z":3},"shapeId":"1742f96c-e3b7-408f-8291-06a125e87355","xaxis":2,"zaxis":-3},{"color":"7eeded","controller":{"containers":null,"controllers":null,"id":2305,"joints":null},"pos":{"x":7,"y":9,"z":12},"shapeId":"b66bf85d-5bee-4461-bee3-b83f371faf04","xaxis":-2,"zaxis":3},{"color":"35086c","controller":{"active":false,"controllers":[{"id":2305}],"id":2304,"joints":null,"mode":0},"pos":{"x":7,"y":9,"z":11},"shapeId":"9f0f56e8-2c31-4d83-996c-d00a9b296c3f","xaxis":-2,"zaxis":3},{"color":"eeaf5c","controller":{"containers":null,"controllers":[{"id":2304}],"id":2303,"joints":null},"pos":{"x":7,"y":9,"z":10},"shapeId":"1742f96c-e3b7-408f-8291-06a125e87355","xaxis":-2,"zaxis":3},{"color":"f06767","controller":{"active":false,"controllers":[{"id":2300}],"id":2302,"joints":null,"mode":0},"pos":{"x":7,"y":8,"z":5},"shapeId":"9f0f56e8-2c31-4d83-996c-d00a9b296c3f","xaxis":2,"zaxis":-3},{"color":"f06767","controller":{"containers":null,"controllers":[{"id":2302}],"id":2301,"joints":null},"pos":{"x":8,"y":8,"z":6},"shapeId":"1742f96c-e3b7-408f-8291-06a125e87355","xaxis":2,"zaxis":-1},{"color":"0a3ee2","controller":{"active":false,"controllers":[{"id":2299}],"id":2300,"joints":null,"mode":0},"pos":{"x":7,"y":9,"z":6},"shapeId":"9f0f56e8-2c31-4d83-996c-d00a9b296c3f","xaxis":-2,"zaxis":3},{"color":"d02525","controller":{"active":false,"controllers":[{"id":2297}],"id":2299,"joints":null,"mode":0},"pos":{"x":7,"y":9,"z":7},"shapeId":"9f0f56e8-2c31-4d83-996c-d00a9b296c3f","xaxis":-2,"zaxis":3},{"color":"df7f01","controller":{"active":false,"controllers":[{"id":2299}],"id":2298,"joints":null,"mode":2},"pos":{"x":7,"y":9,"z":8},"shapeId":"9f0f56e8-2c31-4d83-996c-d00a9b296c3f","xaxis":-2,"zaxis":3},{"color":"7eeded","controller":{"containers":null,"controllers":[{"id":2298},{"id":2304}],"data":"gExVQQAAAAEFBQDQAgAAAAKAc3RhdGUIAA","id":2297,"joints":null},"pos":{"x":7,"y":9,"z":9},"shapeId":"bbd2a902-de99-459e-89cd-3c84de790775","xaxis":-2,"zaxis":3},{"color":"222222","controller":{"active":false,"controllers":[{"id":2302},{"id":2304}],"id":2296,"joints":null,"mode":0},"pos":{"x":7,"y":8,"z":4},"shapeId":"9f0f56e8-2c31-4d83-996c-d00a9b296c3f","xaxis":2,"zaxis":-3},{"color":"eeeeee","controller":{"containers":null,"controllers":[{"id":2287}],"id":2295,"joints":null},"pos":{"x":7,"y":7,"z":3},"shapeId":"1742f96c-e3b7-408f-8291-06a125e87355","xaxis":2,"zaxis":-3},{"color":"7eeded","controller":{"containers":null,"controllers":null,"id":2294,"joints":null},"pos":{"x":7,"y":8,"z":12},"shapeId":"b66bf85d-5bee-4461-bee3-b83f371faf04","xaxis":-2,"zaxis":3},{"color":"35086c","controller":{"active":false,"controllers":[{"id":2294}],"id":2293,"joints":null,"mode":0},"pos":{"x":7,"y":8,"z":11},"shapeId":"9f0f56e8-2c31-4d83-996c-d00a9b296c3f","xaxis":-2,"zaxis":3},{"color":"eeaf5c","controller":{"containers":null,"controllers":[{"id":2293}],"id":2292,"joints":null},"pos":{"x":7,"y":8,"z":10},"shapeId":"1742f96c-e3b7-408f-8291-06a125e87355","xaxis":-2,"zaxis":3},{"color":"f06767","controller":{"active":false,"controllers":[{"id":2289}],"id":2291,"joints":null,"mode":0},"pos":{"x":7,"y":7,"z":5},"shapeId":"9f0f56e8-2c31-4d83-996c-d00a9b296c3f","xaxis":2,"zaxis":-3},{"color":"f06767","controller":{"containers":null,"controllers":[{"id":2291}],"id":2290,"joints":null},"pos":{"x":8,"y":7,"z":6},"shapeId":"1742f96c-e3b7-408f-8291-06a125e87355","xaxis":2,"zaxis":-1},{"color":"0a3ee2","controller":{"active":false,"controllers":[{"id":2288}],"id":2289,"joints":null,"mode":0},"pos":{"x":7,"y":8,"z":6},"shapeId":"9f0f56e8-2c31-4d83-996c-d00a9b296c3f","xaxis":-2,"zaxis":3},{"color":"d02525","controller":{"active":false,"controllers":[{"id":2286}],"id":2288,"joints":null,"mode":0},"pos":{"x":7,"y":8,"z":7},"shapeId":"9f0f56e8-2c31-4d83-996c-d00a9b296c3f","xaxis":-2,"zaxis":3},{"color":"df7f01","controller":{"active":false,"controllers":[{"id":2288}],"id":2287,"joints":null,"mode":2},"pos":{"x":7,"y":8,"z":8},"shapeId":"9f0f56e8-2c31-4d83-996c-d00a9b296c3f","xaxis":-2,"zaxis":3},{"color":"7eeded","controller":{"containers":null,"controllers":[{"id":2287},{"id":2293}],"data":"gExVQQAAAAEFBQDQAgAAAAKAc3RhdGUIAA","id":2286,"joints":null},"pos":{"x":7,"y":8,"z":9},"shapeId":"bbd2a902-de99-459e-89cd-3c84de790775","xaxis":-2,"zaxis":3},{"color":"222222","controller":{"active":false,"controllers":[{"id":2291},{"id":2293}],"id":2285,"joints":null,"mode":0},"pos":{"x":7,"y":7,"z":4},"shapeId":"9f0f56e8-2c31-4d83-996c-d00a9b296c3f","xaxis":2,"zaxis":-3},{"color":"eeeeee","controller":{"containers":null,"controllers":[{"id":2276}],"id":2284,"joints":null},"pos":{"x":7,"y":6,"z":3},"shapeId":"1742f96c-e3b7-408f-8291-06a125e87355","xaxis":2,"zaxis":-3},{"color":"7eeded","controller":{"containers":null,"controllers":null,"id":2283,"joints":null},"pos":{"x":7,"y":7,"z":12},"shapeId":"b66bf85d-5bee-4461-bee3-b83f371faf04","xaxis":-2,"zaxis":3},{"color":"35086c","controller":{"active":false,"controllers":[{"id":2283}],"id":2282,"joints":null,"mode":0},"pos":{"x":7,"y":7,"z":11},"shapeId":"9f0f56e8-2c31-4d83-996c-d00a9b296c3f","xaxis":-2,"zaxis":3},{"color":"eeaf5c","controller":{"containers":null,"controllers":[{"id":2282}],"id":2281,"joints":null},"pos":{"x":7,"y":7,"z":10},"shapeId":"1742f96c-e3b7-408f-8291-06a125e87355","xaxis":-2,"zaxis":3},{"color":"f06767","controller":{"active":false,"controllers":[{"id":2278}],"id":2280,"joints":null,"mode":0},"pos":{"x":7,"y":6,"z":5},"shapeId":"9f0f56e8-2c31-4d83-996c-d00a9b296c3f","xaxis":2,"zaxis":-3},{"color":"f06767","controller":{"containers":null,"controllers":[{"id":2280}],"id":2279,"joints":null},"pos":{"x":8,"y":6,"z":6},"shapeId":"1742f96c-e3b7-408f-8291-06a125e87355","xaxis":2,"zaxis":-1},{"color":"0a3ee2","controller":{"active":false,"controllers":[{"id":2277}],"id":2278,"joints":null,"mode":0},"pos":{"x":7,"y":7,"z":6},"shapeId":"9f0f56e8-2c31-4d83-996c-d00a9b296c3f","xaxis":-2,"zaxis":3},{"color":"d02525","controller":{"active":false,"controllers":[{"id":2275}],"id":2277,"joints":null,"mode":0},"pos":{"x":7,"y":7,"z":7},"shapeId":"9f0f56e8-2c31-4d83-996c-d00a9b296c3f","xaxis":-2,"zaxis":3},{"color":"df7f01","controller":{"active":false,"controllers":[{"id":2277}],"id":2276,"joints":null,"mode":2},"pos":{"x":7,"y":7,"z":8},"shapeId":"9f0f56e8-2c31-4d83-996c-d00a9b296c3f","xaxis":-2,"zaxis":3},{"color":"7eeded","controller":{"containers":null,"controllers":[{"id":2276},{"id":2282}],"data":"gExVQQAAAAEFBQDQAgAAAAKAc3RhdGUIAA","id":2275,"joints":null},"pos":{"x":7,"y":7,"z":9},"shapeId":"bbd2a902-de99-459e-89cd-3c84de790775","xaxis":-2,"zaxis":3},{"color":"222222","controller":{"active":false,"controllers":[{"id":2280},{"id":2282}],"id":2274,"joints":null,"mode":0},"pos":{"x":7,"y":6,"z":4},"shapeId":"9f0f56e8-2c31-4d83-996c-d00a9b296c3f","xaxis":2,"zaxis":-3},{"color":"eeeeee","controller":{"containers":null,"controllers":[{"id":2265}],"id":2273,"joints":null},"pos":{"x":7,"y":5,"z":3},"shapeId":"1742f96c-e3b7-408f-8291-06a125e87355","xaxis":2,"zaxis":-3},{"color":"7eeded","controller":{"containers":null,"controllers":null,"id":2272,"joints":null},"pos":{"x":7,"y":6,"z":12},"shapeId":"b66bf85d-5bee-4461-bee3-b83f371faf04","xaxis":-2,"zaxis":3},{"color":"35086c","controller":{"active":false,"controllers":[{"id":2272}],"id":2271,"joints":null,"mode":0},"pos":{"x":7,"y":6,"z":11},"shapeId":"9f0f56e8-2c31-4d83-996c-d00a9b296c3f","xaxis":-2,"zaxis":3},{"color":"eeaf5c","controller":{"containers":null,"controllers":[{"id":2271}],"id":2270,"joints":null},"pos":{"x":7,"y":6,"z":10},"shapeId":"1742f96c-e3b7-408f-8291-06a125e87355","xaxis":-2,"zaxis":3},{"color":"f06767","controller":{"active":false,"controllers":[{"id":2267}],"id":2269,"joints":null,"mode":0},"pos":{"x":7,"y":5,"z":5},"shapeId":"9f0f56e8-2c31-4d83-996c-d00a9b296c3f","xaxis":2,"zaxis":-3},{"color":"f06767","controller":{"containers":null,"controllers":[{"id":2269}],"id":2268,"joints":null},"pos":{"x":8,"y":5,"z":6},"shapeId":"1742f96c-e3b7-408f-8291-06a125e87355","xaxis":2,"zaxis":-1},{"color":"0a3ee2","controller":{"active":false,"controllers":[{"id":2266}],"id":2267,"joints":null,"mode":0},"pos":{"x":7,"y":6,"z":6},"shapeId":"9f0f56e8-2c31-4d83-996c-d00a9b296c3f","xaxis":-2,"zaxis":3},{"color":"d02525","controller":{"active":false,"controllers":[{"id":2264}],"id":2266,"joints":null,"mode":0},"pos":{"x":7,"y":6,"z":7},"shapeId":"9f0f56e8-2c31-4d83-996c-d00a9b296c3f","xaxis":-2,"zaxis":3},{"color":"df7f01","controller":{"active":false,"controllers":[{"id":2266}],"id":2265,"joints":null,"mode":2},"pos":{"x":7,"y":6,"z":8},"shapeId":"9f0f56e8-2c31-4d83-996c-d00a9b296c3f","xaxis":-2,"zaxis":3},{"color":"7eeded","controller":{"containers":null,"controllers":[{"id":2265},{"id":2271}],"data":"gExVQQAAAAEFBQDQAgAAAAKAc3RhdGUIAA","id":2264,"joints":null},"pos":{"x":7,"y":6,"z":9},"shapeId":"bbd2a902-de99-459e-89cd-3c84de790775","xaxis":-2,"zaxis":3},{"color":"222222","controller":{"active":false,"controllers":[{"id":2269},{"id":2271}],"id":2263,"joints":null,"mode":0},"pos":{"x":7,"y":5,"z":4},"shapeId":"9f0f56e8-2c31-4d83-996c-d00a9b296c3f","xaxis":2,"zaxis":-3},{"color":"eeeeee","controller":{"containers":null,"controllers":[{"id":2254}],"id":2262,"joints":null},"pos":{"x":7,"y":4,"z":3},"shapeId":"1742f96c-e3b7-408f-8291-06a125e87355","xaxis":2,"zaxis":-3},{"color":"7eeded","controller":{"containers":null,"controllers":null,"id":2261,"joints":null},"pos":{"x":7,"y":5,"z":12},"shapeId":"b66bf85d-5bee-4461-bee3-b83f371faf04","xaxis":-2,"zaxis":3},{"color":"35086c","controller":{"active":false,"controllers":[{"id":2261}],"id":2260,"joints":null,"mode":0},"pos":{"x":7,"y":5,"z":11},"shapeId":"9f0f56e8-2c31-4d83-996c-d00a9b296c3f","xaxis":-2,"zaxis":3},{"color":"eeaf5c","controller":{"containers":null,"controllers":[{"id":2260}],"id":2259,"joints":null},"pos":{"x":7,"y":5,"z":10},"shapeId":"1742f96c-e3b7-408f-8291-06a125e87355","xaxis":-2,"zaxis":3},{"color":"f06767","controller":{"active":false,"controllers":[{"id":2256}],"id":2258,"joints":null,"mode":0},"pos":{"x":7,"y":4,"z":5},"shapeId":"9f0f56e8-2c31-4d83-996c-d00a9b296c3f","xaxis":2,"zaxis":-3},{"color":"f06767","controller":{"containers":null,"controllers":[{"id":2258}],"id":2257,"joints":null},"pos":{"x":8,"y":4,"z":6},"shapeId":"1742f96c-e3b7-408f-8291-06a125e87355","xaxis":2,"zaxis":-1},{"color":"0a3ee2","controller":{"active":false,"controllers":[{"id":2255}],"id":2256,"joints":null,"mode":0},"pos":{"x":7,"y":5,"z":6},"shapeId":"9f0f56e8-2c31-4d83-996c-d00a9b296c3f","xaxis":-2,"zaxis":3},{"color":"d02525","controller":{"active":false,"controllers":[{"id":2253}],"id":2255,"joints":null,"mode":0},"pos":{"x":7,"y":5,"z":7},"shapeId":"9f0f56e8-2c31-4d83-996c-d00a9b296c3f","xaxis":-2,"zaxis":3},{"color":"df7f01","controller":{"active":false,"controllers":[{"id":2255}],"id":2254,"joints":null,"mode":2},"pos":{"x":7,"y":5,"z":8},"shapeId":"9f0f56e8-2c31-4d83-996c-d00a9b296c3f","xaxis":-2,"zaxis":3},{"color":"7eeded","controller":{"containers":null,"controllers":[{"id":2254},{"id":2260}],"data":"gExVQQAAAAEFBQDQAgAAAAKAc3RhdGUIAA","id":2253,"joints":null},"pos":{"x":7,"y":5,"z":9},"shapeId":"bbd2a902-de99-459e-89cd-3c84de790775","xaxis":-2,"zaxis":3},{"color":"222222","controller":{"active":false,"controllers":[{"id":2258},{"id":2260}],"id":2252,"joints":null,"mode":0},"pos":{"x":7,"y":4,"z":4},"shapeId":"9f0f56e8-2c31-4d83-996c-d00a9b296c3f","xaxis":2,"zaxis":-3},{"color":"eeeeee","controller":{"containers":null,"controllers":[{"id":2243}],"id":2251,"joints":null},"pos":{"x":7,"y":3,"z":3},"shapeId":"1742f96c-e3b7-408f-8291-06a125e87355","xaxis":2,"zaxis":-3},{"color":"7eeded","controller":{"containers":null,"controllers":null,"id":2250,"joints":null},"pos":{"x":7,"y":4,"z":12},"shapeId":"b66bf85d-5bee-4461-bee3-b83f371faf04","xaxis":-2,"zaxis":3},{"color":"35086c","controller":{"active":false,"controllers":[{"id":2250}],"id":2249,"joints":null,"mode":0},"pos":{"x":7,"y":4,"z":11},"shapeId":"9f0f56e8-2c31-4d83-996c-d00a9b296c3f","xaxis":-2,"zaxis":3},{"color":"eeaf5c","controller":{"containers":null,"controllers":[{"id":2249}],"id":2248,"joints":null},"pos":{"x":7,"y":4,"z":10},"shapeId":"1742f96c-e3b7-408f-8291-06a125e87355","xaxis":-2,"zaxis":3},{"color":"f06767","controller":{"active":false,"controllers":[{"id":2245}],"id":2247,"joints":null,"mode":0},"pos":{"x":7,"y":3,"z":5},"shapeId":"9f0f56e8-2c31-4d83-996c-d00a9b296c3f","xaxis":2,"zaxis":-3},{"color":"f06767","controller":{"containers":null,"controllers":[{"id":2247}],"id":2246,"joints":null},"pos":{"x":8,"y":3,"z":6},"shapeId":"1742f96c-e3b7-408f-8291-06a125e87355","xaxis":2,"zaxis":-1},{"color":"0a3ee2","controller":{"active":false,"controllers":[{"id":2244}],"id":2245,"joints":null,"mode":0},"pos":{"x":7,"y":4,"z":6},"shapeId":"9f0f56e8-2c31-4d83-996c-d00a9b296c3f","xaxis":-2,"zaxis":3},{"color":"d02525","controller":{"active":false,"controllers":[{"id":2242}],"id":2244,"joints":null,"mode":0},"pos":{"x":7,"y":4,"z":7},"shapeId":"9f0f56e8-2c31-4d83-996c-d00a9b296c3f","xaxis":-2,"zaxis":3},{"color":"df7f01","controller":{"active":false,"controllers":[{"id":2244}],"id":2243,"joints":null,"mode":2},"pos":{"x":7,"y":4,"z":8},"shapeId":"9f0f56e8-2c31-4d83-996c-d00a9b296c3f","xaxis":-2,"zaxis":3},{"color":"7eeded","controller":{"containers":null,"controllers":[{"id":2243},{"id":2249}],"data":"gExVQQAAAAEFBQDQAgAAAAKAc3RhdGUIAA","id":2242,"joints":null},"pos":{"x":7,"y":4,"z":9},"shapeId":"bbd2a902-de99-459e-89cd-3c84de790775","xaxis":-2,"zaxis":3},{"color":"222222","controller":{"active":false,"controllers":[{"id":2247},{"id":2249}],"id":2241,"joints":null,"mode":0},"pos":{"x":7,"y":3,"z":4},"shapeId":"9f0f56e8-2c31-4d83-996c-d00a9b296c3f","xaxis":2,"zaxis":-3},{"color":"eeeeee","controller":{"containers":null,"controllers":[{"id":2232}],"id":2240,"joints":null},"pos":{"x":7,"y":2,"z":3},"shapeId":"1742f96c-e3b7-408f-8291-06a125e87355","xaxis":2,"zaxis":-3},{"color":"7eeded","controller":{"containers":null,"controllers":null,"id":2239,"joints":null},"pos":{"x":7,"y":3,"z":12},"shapeId":"b66bf85d-5bee-4461-bee3-b83f371faf04","xaxis":-2,"zaxis":3},{"color":"35086c","controller":{"active":false,"controllers":[{"id":2239}],"id":2238,"joints":null,"mode":0},"pos":{"x":7,"y":3,"z":11},"shapeId":"9f0f56e8-2c31-4d83-996c-d00a9b296c3f","xaxis":-2,"zaxis":3},{"color":"eeaf5c","controller":{"containers":null,"controllers":[{"id":2238}],"id":2237,"joints":null},"pos":{"x":7,"y":3,"z":10},"shapeId":"1742f96c-e3b7-408f-8291-06a125e87355","xaxis":-2,"zaxis":3},{"color":"f06767","controller":{"active":false,"controllers":[{"id":2234}],"id":2236,"joints":null,"mode":0},"pos":{"x":7,"y":2,"z":5},"shapeId":"9f0f56e8-2c31-4d83-996c-d00a9b296c3f","xaxis":2,"zaxis":-3},{"color":"f06767","controller":{"containers":null,"controllers":[{"id":2236}],"id":2235,"joints":null},"pos":{"x":8,"y":2,"z":6},"shapeId":"1742f96c-e3b7-408f-8291-06a125e87355","xaxis":2,"zaxis":-1},{"color":"0a3ee2","controller":{"active":false,"controllers":[{"id":2233}],"id":2234,"joints":null,"mode":0},"pos":{"x":7,"y":3,"z":6},"shapeId":"9f0f56e8-2c31-4d83-996c-d00a9b296c3f","xaxis":-2,"zaxis":3},{"color":"d02525","controller":{"active":false,"controllers":[{"id":2231}],"id":2233,"joints":null,"mode":0},"pos":{"x":7,"y":3,"z":7},"shapeId":"9f0f56e8-2c31-4d83-996c-d00a9b296c3f","xaxis":-2,"zaxis":3},{"color":"df7f01","controller":{"active":false,"controllers":[{"id":2233}],"id":2232,"joints":null,"mode":2},"pos":{"x":7,"y":3,"z":8},"shapeId":"9f0f56e8-2c31-4d83-996c-d00a9b296c3f","xaxis":-2,"zaxis":3},{"color":"7eeded","controller":{"containers":null,"controllers":[{"id":2232},{"id":2238}],"data":"gExVQQAAAAEFBQDQAgAAAAKAc3RhdGUIAA","id":2231,"joints":null},"pos":{"x":7,"y":3,"z":9},"shapeId":"bbd2a902-de99-459e-89cd-3c84de790775","xaxis":-2,"zaxis":3},{"color":"222222","controller":{"active":false,"controllers":[{"id":2236},{"id":2238}],"id":2230,"joints":null,"mode":0},"pos":{"x":7,"y":2,"z":4},"shapeId":"9f0f56e8-2c31-4d83-996c-d00a9b296c3f","xaxis":2,"zaxis":-3},{"color":"eeeeee","controller":{"containers":null,"controllers":[{"id":2221}],"id":2229,"joints":null},"pos":{"x":7,"y":1,"z":3},"shapeId":"1742f96c-e3b7-408f-8291-06a125e87355","xaxis":2,"zaxis":-3},{"color":"7eeded","controller":{"containers":null,"controllers":null,"id":2228,"joints":null},"pos":{"x":7,"y":2,"z":12},"shapeId":"b66bf85d-5bee-4461-bee3-b83f371faf04","xaxis":-2,"zaxis":3},{"color":"35086c","controller":{"active":false,"controllers":[{"id":2228}],"id":2227,"joints":null,"mode":0},"pos":{"x":7,"y":2,"z":11},"shapeId":"9f0f56e8-2c31-4d83-996c-d00a9b296c3f","xaxis":-2,"zaxis":3},{"color":"eeaf5c","controller":{"containers":null,"controllers":[{"id":2227}],"id":2226,"joints":null},"pos":{"x":7,"y":2,"z":10},"shapeId":"1742f96c-e3b7-408f-8291-06a125e87355","xaxis":-2,"zaxis":3},{"color":"f06767","controller":{"active":false,"controllers":[{"id":2223}],"id":2225,"joints":null,"mode":0},"pos":{"x":7,"y":1,"z":5},"shapeId":"9f0f56e8-2c31-4d83-996c-d00a9b296c3f","xaxis":2,"zaxis":-3},{"color":"f06767","controller":{"containers":null,"controllers":[{"id":2225}],"id":2224,"joints":null},"pos":{"x":8,"y":1,"z":6},"shapeId":"1742f96c-e3b7-408f-8291-06a125e87355","xaxis":2,"zaxis":-1},{"color":"0a3ee2","controller":{"active":false,"controllers":[{"id":2222}],"id":2223,"joints":null,"mode":0},"pos":{"x":7,"y":2,"z":6},"shapeId":"9f0f56e8-2c31-4d83-996c-d00a9b296c3f","xaxis":-2,"zaxis":3},{"color":"d02525","controller":{"active":false,"controllers":[{"id":2220}],"id":2222,"joints":null,"mode":0},"pos":{"x":7,"y":2,"z":7},"shapeId":"9f0f56e8-2c31-4d83-996c-d00a9b296c3f","xaxis":-2,"zaxis":3},{"color":"df7f01","controller":{"active":false,"controllers":[{"id":2222}],"id":2221,"joints":null,"mode":2},"pos":{"x":7,"y":2,"z":8},"shapeId":"9f0f56e8-2c31-4d83-996c-d00a9b296c3f","xaxis":-2,"zaxis":3},{"color":"7eeded","controller":{"containers":null,"controllers":[{"id":2221},{"id":2227}],"data":"gExVQQAAAAEFBQDQAgAAAAKAc3RhdGUIAA","id":2220,"joints":null},"pos":{"x":7,"y":2,"z":9},"shapeId":"bbd2a902-de99-459e-89cd-3c84de790775","xaxis":-2,"zaxis":3},{"color":"222222","controller":{"active":false,"controllers":[{"id":2225},{"id":2227}],"id":2219,"joints":null,"mode":0},"pos":{"x":7,"y":1,"z":4},"shapeId":"9f0f56e8-2c31-4d83-996c-d00a9b296c3f","xaxis":2,"zaxis":-3},{"color":"eeeeee","controller":{"containers":null,"controllers":[{"id":2210}],"id":2218,"joints":null},"pos":{"x":7,"y":0,"z":3},"shapeId":"1742f96c-e3b7-408f-8291-06a125e87355","xaxis":2,"zaxis":-3},{"color":"7eeded","controller":{"containers":null,"controllers":null,"id":2217,"joints":null},"pos":{"x":7,"y":1,"z":12},"shapeId":"b66bf85d-5bee-4461-bee3-b83f371faf04","xaxis":-2,"zaxis":3},{"color":"35086c","controller":{"active":false,"controllers":[{"id":2217}],"id":2216,"joints":null,"mode":0},"pos":{"x":7,"y":1,"z":11},"shapeId":"9f0f56e8-2c31-4d83-996c-d00a9b296c3f","xaxis":-2,"zaxis":3},{"color":"eeaf5c","controller":{"containers":null,"controllers":[{"id":2216}],"id":2215,"joints":null},"pos":{"x":7,"y":1,"z":10},"shapeId":"1742f96c-e3b7-408f-8291-06a125e87355","xaxis":-2,"zaxis":3},{"color":"f06767","controller":{"active":false,"controllers":[{"id":2212}],"id":2214,"joints":null,"mode":0},"pos":{"x":7,"y":0,"z":5},"shapeId":"9f0f56e8-2c31-4d83-996c-d00a9b296c3f","xaxis":2,"zaxis":-3},{"color":"f06767","controller":{"containers":null,"controllers":[{"id":2214}],"id":2213,"joints":null},"pos":{"x":8,"y":0,"z":6},"shapeId":"1742f96c-e3b7-408f-8291-06a125e87355","xaxis":2,"zaxis":-1},{"color":"0a3ee2","controller":{"active":false,"controllers":[{"id":2211}],"id":2212,"joints":null,"mode":0},"pos":{"x":7,"y":1,"z":6},"shapeId":"9f0f56e8-2c31-4d83-996c-d00a9b296c3f","xaxis":-2,"zaxis":3},{"color":"d02525","controller":{"active":false,"controllers":[{"id":2209}],"id":2211,"joints":null,"mode":0},"pos":{"x":7,"y":1,"z":7},"shapeId":"9f0f56e8-2c31-4d83-996c-d00a9b296c3f","xaxis":-2,"zaxis":3},{"color":"df7f01","controller":{"active":false,"controllers":[{"id":2211}],"id":2210,"joints":null,"mode":2},"pos":{"x":7,"y":1,"z":8},"shapeId":"9f0f56e8-2c31-4d83-996c-d00a9b296c3f","xaxis":-2,"zaxis":3},{"color":"7eeded","controller":{"containers":null,"controllers":[{"id":2210},{"id":2216}],"data":"gExVQQAAAAEFBQDQAgAAAAKAc3RhdGUIAA","id":2209,"joints":null},"pos":{"x":7,"y":1,"z":9},"shapeId":"bbd2a902-de99-459e-89cd-3c84de790775","xaxis":-2,"zaxis":3},{"color":"222222","controller":{"active":false,"controllers":[{"id":2214},{"id":2216}],"id":2208,"joints":null,"mode":0},"pos":{"x":7,"y":0,"z":4},"shapeId":"9f0f56e8-2c31-4d83-996c-d00a9b296c3f","xaxis":2,"zaxis":-3},{"color":"eeeeee","controller":{"containers":null,"controllers":[{"id":2199}],"id":2207,"joints":null},"pos":{"x":7,"y":-1,"z":3},"shapeId":"1742f96c-e3b7-408f-8291-06a125e87355","xaxis":2,"zaxis":-3},{"color":"7eeded","controller":{"containers":null,"controllers":null,"id":2206,"joints":null},"pos":{"x":7,"y":0,"z":12},"shapeId":"b66bf85d-5bee-4461-bee3-b83f371faf04","xaxis":-2,"zaxis":3},{"color":"35086c","controller":{"active":false,"controllers":[{"id":2206}],"id":2205,"joints":null,"mode":0},"pos":{"x":7,"y":0,"z":11},"shapeId":"9f0f56e8-2c31-4d83-996c-d00a9b296c3f","xaxis":-2,"zaxis":3},{"color":"eeaf5c","controller":{"containers":null,"controllers":[{"id":2205}],"id":2204,"joints":null},"pos":{"x":7,"y":0,"z":10},"shapeId":"1742f96c-e3b7-408f-8291-06a125e87355","xaxis":-2,"zaxis":3},{"color":"f06767","controller":{"active":false,"controllers":[{"id":2201}],"id":2203,"joints":null,"mode":0},"pos":{"x":7,"y":-1,"z":5},"shapeId":"9f0f56e8-2c31-4d83-996c-d00a9b296c3f","xaxis":2,"zaxis":-3},{"color":"f06767","controller":{"containers":null,"controllers":[{"id":2203}],"id":2202,"joints":null},"pos":{"x":8,"y":-1,"z":6},"shapeId":"1742f96c-e3b7-408f-8291-06a125e87355","xaxis":2,"zaxis":-1},{"color":"0a3ee2","controller":{"active":false,"controllers":[{"id":2200}],"id":2201,"joints":null,"mode":0},"pos":{"x":7,"y":0,"z":6},"shapeId":"9f0f56e8-2c31-4d83-996c-d00a9b296c3f","xaxis":-2,"zaxis":3},{"color":"d02525","controller":{"active":false,"controllers":[{"id":2198}],"id":2200,"joints":null,"mode":0},"pos":{"x":7,"y":0,"z":7},"shapeId":"9f0f56e8-2c31-4d83-996c-d00a9b296c3f","xaxis":-2,"zaxis":3},{"color":"df7f01","controller":{"active":false,"controllers":[{"id":2200}],"id":2199,"joints":null,"mode":2},"pos":{"x":7,"y":0,"z":8},"shapeId":"9f0f56e8-2c31-4d83-996c-d00a9b296c3f","xaxis":-2,"zaxis":3},{"color":"7eeded","controller":{"containers":null,"controllers":[{"id":2199},{"id":2205}],"data":"gExVQQAAAAEFBQDQAgAAAAKAc3RhdGUIAA","id":2198,"joints":null},"pos":{"x":7,"y":0,"z":9},"shapeId":"bbd2a902-de99-459e-89cd-3c84de790775","xaxis":-2,"zaxis":3},{"color":"222222","controller":{"active":false,"controllers":[{"id":2203},{"id":2205}],"id":2197,"joints":null,"mode":0},"pos":{"x":7,"y":-1,"z":4},"shapeId":"9f0f56e8-2c31-4d83-996c-d00a9b296c3f","xaxis":2,"zaxis":-3},{"color":"eeeeee","controller":{"containers":null,"controllers":[{"id":2188}],"id":2196,"joints":null},"pos":{"x":7,"y":-2,"z":3},"shapeId":"1742f96c-e3b7-408f-8291-06a125e87355","xaxis":2,"zaxis":-3},{"color":"7eeded","controller":{"containers":null,"controllers":null,"id":2195,"joints":null},"pos":{"x":7,"y":-1,"z":12},"shapeId":"b66bf85d-5bee-4461-bee3-b83f371faf04","xaxis":-2,"zaxis":3},{"color":"35086c","controller":{"active":false,"controllers":[{"id":2195}],"id":2194,"joints":null,"mode":0},"pos":{"x":7,"y":-1,"z":11},"shapeId":"9f0f56e8-2c31-4d83-996c-d00a9b296c3f","xaxis":-2,"zaxis":3},{"color":"eeaf5c","controller":{"containers":null,"controllers":[{"id":2194}],"id":2193,"joints":null},"pos":{"x":7,"y":-1,"z":10},"shapeId":"1742f96c-e3b7-408f-8291-06a125e87355","xaxis":-2,"zaxis":3},{"color":"f06767","controller":{"active":false,"controllers":[{"id":2190}],"id":2192,"joints":null,"mode":0},"pos":{"x":7,"y":-2,"z":5},"shapeId":"9f0f56e8-2c31-4d83-996c-d00a9b296c3f","xaxis":2,"zaxis":-3},{"color":"f06767","controller":{"containers":null,"controllers":[{"id":2192}],"id":2191,"joints":null},"pos":{"x":8,"y":-2,"z":6},"shapeId":"1742f96c-e3b7-408f-8291-06a125e87355","xaxis":2,"zaxis":-1},{"color":"0a3ee2","controller":{"active":false,"controllers":[{"id":2189}],"id":2190,"joints":null,"mode":0},"pos":{"x":7,"y":-1,"z":6},"shapeId":"9f0f56e8-2c31-4d83-996c-d00a9b296c3f","xaxis":-2,"zaxis":3},{"color":"d02525","controller":{"active":false,"controllers":[{"id":2187}],"id":2189,"joints":null,"mode":0},"pos":{"x":7,"y":-1,"z":7},"shapeId":"9f0f56e8-2c31-4d83-996c-d00a9b296c3f","xaxis":-2,"zaxis":3},{"color":"df7f01","controller":{"active":false,"controllers":[{"id":2189}],"id":2188,"joints":null,"mode":2},"pos":{"x":7,"y":-1,"z":8},"shapeId":"9f0f56e8-2c31-4d83-996c-d00a9b296c3f","xaxis":-2,"zaxis":3},{"color":"7eeded","controller":{"containers":null,"controllers":[{"id":2188},{"id":2194}],"data":"gExVQQAAAAEFBQDQAgAAAAKAc3RhdGUIAA","id":2187,"joints":null},"pos":{"x":7,"y":-1,"z":9},"shapeId":"bbd2a902-de99-459e-89cd-3c84de790775","xaxis":-2,"zaxis":3},{"color":"222222","controller":{"active":false,"controllers":[{"id":2192},{"id":2194}],"id":2186,"joints":null,"mode":0},"pos":{"x":7,"y":-2,"z":4},"shapeId":"9f0f56e8-2c31-4d83-996c-d00a9b296c3f","xaxis":2,"zaxis":-3},{"color":"eeeeee","controller":{"containers":null,"controllers":[{"id":2178}],"id":2175,"joints":null},"pos":{"x":7,"y":-3,"z":3},"shapeId":"1742f96c-e3b7-408f-8291-06a125e87355","xaxis":2,"zaxis":-3},{"color":"7eeded","controller":{"containers":null,"controllers":null,"id":2185,"joints":null},"pos":{"x":7,"y":-2,"z":12},"shapeId":"b66bf85d-5bee-4461-bee3-b83f371faf04","xaxis":-2,"zaxis":3},{"color":"35086c","controller":{"active":false,"controllers":[{"id":2185}],"id":2184,"joints":null,"mode":0},"pos":{"x":7,"y":-2,"z":11},"shapeId":"9f0f56e8-2c31-4d83-996c-d00a9b296c3f","xaxis":-2,"zaxis":3},{"color":"eeaf5c","controller":{"containers":null,"controllers":[{"id":2184}],"id":2183,"joints":null},"pos":{"x":7,"y":-2,"z":10},"shapeId":"1742f96c-e3b7-408f-8291-06a125e87355","xaxis":-2,"zaxis":3},{"color":"f06767","controller":{"active":false,"controllers":[{"id":2180}],"id":2182,"joints":null,"mode":0},"pos":{"x":7,"y":-3,"z":5},"shapeId":"9f0f56e8-2c31-4d83-996c-d00a9b296c3f","xaxis":2,"zaxis":-3},{"color":"f06767","controller":{"containers":null,"controllers":[{"id":2182}],"id":2181,"joints":null},"pos":{"x":8,"y":-3,"z":6},"shapeId":"1742f96c-e3b7-408f-8291-06a125e87355","xaxis":2,"zaxis":-1},{"color":"0a3ee2","controller":{"active":false,"controllers":[{"id":2179}],"id":2180,"joints":null,"mode":0},"pos":{"x":7,"y":-2,"z":6},"shapeId":"9f0f56e8-2c31-4d83-996c-d00a9b296c3f","xaxis":-2,"zaxis":3},{"color":"d02525","controller":{"active":false,"controllers":[{"id":2177}],"id":2179,"joints":null,"mode":0},"pos":{"x":7,"y":-2,"z":7},"shapeId":"9f0f56e8-2c31-4d83-996c-d00a9b296c3f","xaxis":-2,"zaxis":3},{"color":"df7f01","controller":{"active":false,"controllers":[{"id":2179}],"id":2178,"joints":null,"mode":2},"pos":{"x":7,"y":-2,"z":8},"shapeId":"9f0f56e8-2c31-4d83-996c-d00a9b296c3f","xaxis":-2,"zaxis":3},{"color":"7eeded","controller":{"containers":null,"controllers":[{"id":2178},{"id":2184}],"data":"gExVQQAAAAEFBQDQAgAAAAKAc3RhdGUIAA","id":2177,"joints":null},"pos":{"x":7,"y":-2,"z":9},"shapeId":"bbd2a902-de99-459e-89cd-3c84de790775","xaxis":-2,"zaxis":3},{"color":"222222","controller":{"active":false,"controllers":[{"id":2182},{"id":2184}],"id":2176,"joints":null,"mode":0},"pos":{"x":7,"y":-3,"z":4},"shapeId":"9f0f56e8-2c31-4d83-996c-d00a9b296c3f","xaxis":2,"zaxis":-3},{"color":"df7f01","controller":{"active":false,"controllers":null,"id":1997,"joints":null,"mode":0},"pos":{"x":7,"y":10,"z":-8},"shapeId":"9f0f56e8-2c31-4d83-996c-d00a9b296c3f","xaxis":-1,"zaxis":2},{"color":"df7f01","controller":{"active":false,"controllers":null,"id":1996,"joints":null,"mode":0},"pos":{"x":7,"y":11,"z":-8},"shapeId":"9f0f56e8-2c31-4d83-996c-d00a9b296c3f","xaxis":-1,"zaxis":2},{"color":"df7f01","controller":{"active":false,"controllers":null,"id":1995,"joints":null,"mode":0},"pos":{"x":7,"y":12,"z":-8},"shapeId":"9f0f56e8-2c31-4d83-996c-d00a9b296c3f","xaxis":-1,"zaxis":2},{"color":"df7f01","controller":{"active":false,"controllers":null,"id":1994,"joints":null,"mode":0},"pos":{"x":7,"y":8,"z":-8},"shapeId":"9f0f56e8-2c31-4d83-996c-d00a9b296c3f","xaxis":-1,"zaxis":2},{"color":"df7f01","controller":{"active":false,"controllers":null,"id":1993,"joints":null,"mode":0},"pos":{"x":7,"y":7,"z":-8},"shapeId":"9f0f56e8-2c31-4d83-996c-d00a9b296c3f","xaxis":-1,"zaxis":2},{"color":"df7f01","controller":{"active":false,"controllers":null,"id":1992,"joints":null,"mode":0},"pos":{"x":7,"y":6,"z":-8},"shapeId":"9f0f56e8-2c31-4d83-996c-d00a9b296c3f","xaxis":-1,"zaxis":2},{"color":"df7f01","controller":{"active":false,"controllers":null,"id":1991,"joints":null,"mode":0},"pos":{"x":7,"y":5,"z":-8},"shapeId":"9f0f56e8-2c31-4d83-996c-d00a9b296c3f","xaxis":-1,"zaxis":2},{"color":"df7f01","controller":{"active":false,"controllers":null,"id":1990,"joints":null,"mode":0},"pos":{"x":7,"y":4,"z":-8},"shapeId":"9f0f56e8-2c31-4d83-996c-d00a9b296c3f","xaxis":-1,"zaxis":2},{"color":"df7f01","controller":{"active":false,"controllers":null,"id":1989,"joints":null,"mode":0},"pos":{"x":7,"y":3,"z":-8},"shapeId":"9f0f56e8-2c31-4d83-996c-d00a9b296c3f","xaxis":-1,"zaxis":2},{"color":"df7f01","controller":{"active":false,"controllers":null,"id":1988,"joints":null,"mode":0},"pos":{"x":7,"y":1,"z":-8},"shapeId":"9f0f56e8-2c31-4d83-996c-d00a9b296c3f","xaxis":-1,"zaxis":2},{"color":"df7f01","controller":{"active":false,"controllers":null,"id":1987,"joints":null,"mode":0},"pos":{"x":7,"y":2,"z":-8},"shapeId":"9f0f56e8-2c31-4d83-996c-d00a9b296c3f","xaxis":-1,"zaxis":2},{"color":"df7f01","controller":{"active":false,"controllers":null,"id":1986,"joints":null,"mode":0},"pos":{"x":7,"y":0,"z":-8},"shapeId":"9f0f56e8-2c31-4d83-996c-d00a9b296c3f","xaxis":-1,"zaxis":2},{"color":"df7f01","controller":{"active":false,"controllers":null,"id":1985,"joints":null,"mode":0},"pos":{"x":7,"y":-2,"z":-8},"shapeId":"9f0f56e8-2c31-4d83-996c-d00a9b296c3f","xaxis":-1,"zaxis":2},{"color":"df7f01","controller":{"active":false,"controllers":null,"id":1984,"joints":null,"mode":0},"pos":{"x":7,"y":-1,"z":-8},"shapeId":"9f0f56e8-2c31-4d83-996c-d00a9b296c3f","xaxis":-1,"zaxis":2},{"color":"df7f01","controller":{"active":false,"controllers":null,"id":1983,"joints":null,"mode":0},"pos":{"x":7,"y":-3,"z":-8},"shapeId":"9f0f56e8-2c31-4d83-996c-d00a9b296c3f","xaxis":-1,"zaxis":2},{"color":"df7f01","controller":{"active":false,"controllers":null,"id":1998,"joints":null,"mode":0},"pos":{"x":7,"y":9,"z":-8},"shapeId":"9f0f56e8-2c31-4d83-996c-d00a9b296c3f","xaxis":-1,"zaxis":2},{"bounds":{"x":14,"y":16,"z":1},"color":"675f51","pos":{"x":-7,"y":-3,"z":-9},"shapeId":"8aedf6c2-94e1-4506-89d4-a0227c552f1e","xaxis":1,"zaxis":3},{"color":"df7f01","controller":{"active":false,"controllers":[{"id":2329}],"id":1982,"joints":null,"mode":0},"pos":{"x":8,"y":13,"z":-9},"shapeId":"9f0f56e8-2c31-4d83-996c-d00a9b296c3f","xaxis":-2,"zaxis":-1},{"color":"df7f01","controller":{"active":false,"controllers":[{"id":2349}],"id":1981,"joints":null,"mode":0},"pos":{"x":8,"y":12,"z":-9},"shapeId":"9f0f56e8-2c31-4d83-996c-d00a9b296c3f","xaxis":-2,"zaxis":-1},{"color":"df7f01","controller":{"active":false,"controllers":[{"id":2318}],"id":1980,"joints":null,"mode":0},"pos":{"x":8,"y":11,"z":-9},"shapeId":"9f0f56e8-2c31-4d83-996c-d00a9b296c3f","xaxis":-2,"zaxis":-1},{"color":"df7f01","controller":{"active":false,"controllers":[{"id":2307}],"id":1979,"joints":null,"mode":0},"pos":{"x":8,"y":10,"z":-9},"shapeId":"9f0f56e8-2c31-4d83-996c-d00a9b296c3f","xaxis":-2,"zaxis":-1},{"color":"df7f01","controller":{"active":false,"controllers":[{"id":2296}],"id":1978,"joints":null,"mode":0},"pos":{"x":8,"y":9,"z":-9},"shapeId":"9f0f56e8-2c31-4d83-996c-d00a9b296c3f","xaxis":-2,"zaxis":-1},{"color":"df7f01","controller":{"active":false,"controllers":[{"id":2285}],"id":1977,"joints":null,"mode":0},"pos":{"x":8,"y":8,"z":-9},"shapeId":"9f0f56e8-2c31-4d83-996c-d00a9b296c3f","xaxis":-2,"zaxis":-1},{"color":"df7f01","controller":{"active":false,"controllers":[{"id":2274}],"id":1976,"joints":null,"mode":0},"pos":{"x":8,"y":7,"z":-9},"shapeId":"9f0f56e8-2c31-4d83-996c-d00a9b296c3f","xaxis":-2,"zaxis":-1},{"color":"df7f01","controller":{"active":false,"controllers":[{"id":2263}],"id":1975,"joints":null,"mode":0},"pos":{"x":8,"y":6,"z":-9},"shapeId":"9f0f56e8-2c31-4d83-996c-d00a9b296c3f","xaxis":-2,"zaxis":-1},{"color":"df7f01","controller":{"active":false,"controllers":[{"id":2252}],"id":1974,"joints":null,"mode":0},"pos":{"x":8,"y":5,"z":-9},"shapeId":"9f0f56e8-2c31-4d83-996c-d00a9b296c3f","xaxis":-2,"zaxis":-1},{"color":"df7f01","controller":{"active":false,"controllers":[{"id":2230}],"id":1973,"joints":null,"mode":0},"pos":{"x":8,"y":3,"z":-9},"shapeId":"9f0f56e8-2c31-4d83-996c-d00a9b296c3f","xaxis":-2,"zaxis":-1},{"color":"df7f01","controller":{"active":false,"controllers":[{"id":2241}],"id":1972,"joints":null,"mode":0},"pos":{"x":8,"y":4,"z":-9},"shapeId":"9f0f56e8-2c31-4d83-996c-d00a9b296c3f","xaxis":-2,"zaxis":-1},{"color":"df7f01","controller":{"active":false,"controllers":[{"id":2219}],"id":1971,"joints":null,"mode":0},"pos":{"x":8,"y":2,"z":-9},"shapeId":"9f0f56e8-2c31-4d83-996c-d00a9b296c3f","xaxis":-2,"zaxis":-1},{"color":"df7f01","controller":{"active":false,"controllers":[{"id":2208}],"id":1970,"joints":null,"mode":0},"pos":{"x":8,"y":1,"z":-9},"shapeId":"9f0f56e8-2c31-4d83-996c-d00a9b296c3f","xaxis":-2,"zaxis":-1},{"color":"df7f01","controller":{"active":false,"controllers":[{"id":2197}],"id":1969,"joints":null,"mode":0},"pos":{"x":8,"y":0,"z":-9},"shapeId":"9f0f56e8-2c31-4d83-996c-d00a9b296c3f","xaxis":-2,"zaxis":-1},{"color":"df7f01","controller":{"active":false,"controllers":[{"id":2186}],"id":1968,"joints":null,"mode":0},"pos":{"x":8,"y":-1,"z":-9},"shapeId":"9f0f56e8-2c31-4d83-996c-d00a9b296c3f","xaxis":-2,"zaxis":-1},{"color":"df7f01","controller":{"active":false,"controllers":[{"id":2176}],"id":1967,"joints":null,"mode":0},"pos":{"x":8,"y":-2,"z":-9},"shapeId":"9f0f56e8-2c31-4d83-996c-d00a9b296c3f","xaxis":-2,"zaxis":-1},{"color":"df7f01","controller":{"active":false,"controllers":[{"id":1662}],"id":1966,"joints":null,"mode":0},"pos":{"x":9,"y":13,"z":-9},"shapeId":"9f0f56e8-2c31-4d83-996c-d00a9b296c3f","xaxis":-2,"zaxis":-1},{"color":"df7f01","controller":{"active":false,"controllers":[{"id":1750}],"id":1965,"joints":null,"mode":0},"pos":{"x":9,"y":12,"z":-9},"shapeId":"9f0f56e8-2c31-4d83-996c-d00a9b296c3f","xaxis":-2,"zaxis":-1},{"color":"df7f01","controller":{"active":false,"controllers":[{"id":1761}],"id":1964,"joints":null,"mode":0},"pos":{"x":9,"y":11,"z":-9},"shapeId":"9f0f56e8-2c31-4d83-996c-d00a9b296c3f","xaxis":-2,"zaxis":-1},{"color":"df7f01","controller":{"active":false,"controllers":[{"id":1772}],"id":1963,"joints":null,"mode":0},"pos":{"x":9,"y":10,"z":-9},"shapeId":"9f0f56e8-2c31-4d83-996c-d00a9b296c3f","xaxis":-2,"zaxis":-1},{"color":"df7f01","controller":{"active":false,"controllers":[{"id":1783}],"id":1962,"joints":null,"mode":0},"pos":{"x":9,"y":9,"z":-9},"shapeId":"9f0f56e8-2c31-4d83-996c-d00a9b296c3f","xaxis":-2,"zaxis":-1},{"color":"df7f01","controller":{"active":false,"controllers":[{"id":1794}],"id":1961,"joints":null,"mode":0},"pos":{"x":9,"y":8,"z":-9},"shapeId":"9f0f56e8-2c31-4d83-996c-d00a9b296c3f","xaxis":-2,"zaxis":-1},{"color":"df7f01","controller":{"active":false,"controllers":[{"id":1805}],"id":1960,"joints":null,"mode":0},"pos":{"x":9,"y":7,"z":-9},"shapeId":"9f0f56e8-2c31-4d83-996c-d00a9b296c3f","xaxis":-2,"zaxis":-1},{"color":"df7f01","controller":{"active":false,"controllers":[{"id":1816}],"id":1959,"joints":null,"mode":0},"pos":{"x":9,"y":6,"z":-9},"shapeId":"9f0f56e8-2c31-4d83-996c-d00a9b296c3f","xaxis":-2,"zaxis":-1},{"color":"df7f01","controller":{"active":false,"controllers":[{"id":1827}],"id":1958,"joints":null,"mode":0},"pos":{"x":9,"y":5,"z":-9},"shapeId":"9f0f56e8-2c31-4d83-996c-d00a9b296c3f","xaxis":-2,"zaxis":-1},{"color":"df7f01","controller":{"active":false,"controllers":[{"id":1838}],"id":1957,"joints":null,"mode":0},"pos":{"x":9,"y":4,"z":-9},"shapeId":"9f0f56e8-2c31-4d83-996c-d00a9b296c3f","xaxis":-2,"zaxis":-1},{"color":"df7f01","controller":{"active":false,"controllers":[{"id":1849}],"id":1956,"joints":null,"mode":0},"pos":{"x":9,"y":3,"z":-9},"shapeId":"9f0f56e8-2c31-4d83-996c-d00a9b296c3f","xaxis":-2,"zaxis":-1},{"color":"df7f01","controller":{"active":false,"controllers":[{"id":1860}],"id":1955,"joints":null,"mode":0},"pos":{"x":9,"y":2,"z":-9},"shapeId":"9f0f56e8-2c31-4d83-996c-d00a9b296c3f","xaxis":-2,"zaxis":-1},{"color":"df7f01","controller":{"active":false,"controllers":[{"id":1871}],"id":1953,"joints":null,"mode":0},"pos":{"x":9,"y":1,"z":-9},"shapeId":"9f0f56e8-2c31-4d83-996c-d00a9b296c3f","xaxis":-2,"zaxis":-1},{"color":"df7f01","controller":{"active":false,"controllers":[{"id":1882}],"id":1952,"joints":null,"mode":0},"pos":{"x":9,"y":0,"z":-9},"shapeId":"9f0f56e8-2c31-4d83-996c-d00a9b296c3f","xaxis":-2,"zaxis":-1},{"color":"df7f01","controller":{"active":false,"controllers":[{"id":1893}],"id":1951,"joints":null,"mode":0},"pos":{"x":9,"y":-1,"z":-9},"shapeId":"9f0f56e8-2c31-4d83-996c-d00a9b296c3f","xaxis":-2,"zaxis":-1},{"color":"df7f01","controller":{"active":false,"controllers":[{"id":1904}],"id":1950,"joints":null,"mode":0},"pos":{"x":9,"y":-2,"z":-9},"shapeId":"9f0f56e8-2c31-4d83-996c-d00a9b296c3f","xaxis":-2,"zaxis":-1},{"color":"df7f01","controller":{"active":false,"controllers":[{"id":1951},{"id":1953},{"id":1956},{"id":1958},{"id":1960},{"id":1962},{"id":1964},{"id":1966},{"id":1968},{"id":1970},{"id":1973},{"id":1974},{"id":1976},{"id":1978},{"id":1980},{"id":1982}],"id":1942,"joints":null,"mode":0},"pos":{"x":15,"y":10,"z":-9},"shapeId":"9f0f56e8-2c31-4d83-996c-d00a9b296c3f","xaxis":-2,"zaxis":-1},{"bounds":{"x":14,"y":7,"z":1},"color":"675f51","pos":{"x":-6,"y":-10,"z":-10},"shapeId":"8aedf6c2-94e1-4506-89d4-a0227c552f1e","xaxis":1,"zaxis":3},{"color":"df7f01","controller":{"active":false,"controllers":[{"id":1955},{"id":1956},{"id":1957},{"id":1958},{"id":1963},{"id":1964},{"id":1965},{"id":1966},{"id":1971},{"id":1973},{"id":1972},{"id":1974},{"id":1979},{"id":1980},{"id":1981},{"id":1982}],"id":1940,"joints":null,"mode":0},"pos":{"x":15,"y":4,"z":-9},"shapeId":"9f0f56e8-2c31-4d83-996c-d00a9b296c3f","xaxis":-2,"zaxis":-1},{"bounds":{"x":13,"y":14,"z":1},"color":"675f51","pos":{"x":9,"y":-2,"z":-10},"shapeId":"8aedf6c2-94e1-4506-89d4-a0227c552f1e","xaxis":1,"zaxis":3},{"color":"df7f01","controller":{"active":false,"controllers":[{"id":1959},{"id":1960},{"id":1961},{"id":1962},{"id":1963},{"id":1964},{"id":1965},{"id":1966},{"id":1975},{"id":1976},{"id":1977},{"id":1978},{"id":1979},{"id":1980},{"id":1981},{"id":1982}],"id":1939,"joints":null,"mode":0},"pos":{"x":15,"y":1,"z":-9},"shapeId":"9f0f56e8-2c31-4d83-996c-d00a9b296c3f","xaxis":-2,"zaxis":-1},{"color":"df7f01","controller":{"active":false,"controllers":[{"id":1952},{"id":1953},{"id":1957},{"id":1958},{"id":1961},{"id":1962},{"id":1965},{"id":1966},{"id":1969},{"id":1970},{"id":1972},{"id":1974},{"id":1977},{"id":1978},{"id":1981},{"id":1982}],"id":1941,"joints":null,"mode":0},"pos":{"x":15,"y":7,"z":-9},"shapeId":"9f0f56e8-2c31-4d83-996c-d00a9b296c3f","xaxis":-2,"zaxis":-1},{"color":"df7f01","controller":{"active":false,"controllers":[{"id":1967},{"id":1968},{"id":1969},{"id":1970},{"id":1971},{"id":1973},{"id":1972},{"id":1974},{"id":1975},{"id":1976},{"id":1977},{"id":1979},{"id":1980},{"id":1981},{"id":1982}],"id":1944,"joints":null,"mode":0},"pos":{"x":6,"y":-8,"z":-9},"shapeId":"9f0f56e8-2c31-4d83-996c-d00a9b296c3f","xaxis":-2,"zaxis":-1},{"color":"df7f01","controller":{"active":false,"controllers":[{"id":1983},{"id":1985},{"id":1984},{"id":1986},{"id":1988},{"id":1987},{"id":1989},{"id":1990},{"id":1991},{"id":1992},{"id":1993},{"id":1994},{"id":1998},{"id":1997},{"id":1996},{"id":1995}],"id":1947,"joints":null,"mode":0},"pos":{"x":3,"y":-8,"z":-9},"shapeId":"9f0f56e8-2c31-4d83-996c-d00a9b296c3f","xaxis":-2,"zaxis":-1},{"color":"df7f01","controller":{"active":false,"controllers":null,"id":1948,"joints":null,"mode":0},"pos":{"x":0,"y":-8,"z":-9},"shapeId":"9f0f56e8-2c31-4d83-996c-d00a9b296c3f","xaxis":-2,"zaxis":-1},{"color":"df7f01","controller":{"active":false,"controllers":null,"id":1949,"joints":null,"mode":0},"pos":{"x":-3,"y":-8,"z":-9},"shapeId":"9f0f56e8-2c31-4d83-996c-d00a9b296c3f","xaxis":-2,"zaxis":-1},{"bounds":{"x":1,"y":1,"z":1},"color":"675f51","pos":{"x":9,"y":-4,"z":2},"shapeId":"8aedf6c2-94e1-4506-89d4-a0227c552f1e","xaxis":1,"zaxis":3},{"bounds":{"x":1,"y":1,"z":13},"color":"675f51","pos":{"x":8,"y":-4,"z":-10},"shapeId":"8aedf6c2-94e1-4506-89d4-a0227c552f1e","xaxis":1,"zaxis":3},{"bounds":{"x":1,"y":1,"z":13},"color":"675f51","pos":{"x":8,"y":13,"z":-10},"shapeId":"8aedf6c2-94e1-4506-89d4-a0227c552f1e","xaxis":1,"zaxis":3},{"bounds":{"x":1,"y":1,"z":12},"color":"675f51","pos":{"x":-7,"y":-4,"z":-10},"shapeId":"8aedf6c2-94e1-4506-89d4-a0227c552f1e","xaxis":1,"zaxis":3},{"bounds":{"x":1,"y":1,"z":12},"color":"675f51","pos":{"x":-8,"y":-3,"z":-10},"shapeId":"8aedf6c2-94e1-4506-89d4-a0227c552f1e","xaxis":1,"zaxis":3},{"bounds":{"x":1,"y":1,"z":12},"color":"675f51","pos":{"x":-8,"y":12,"z":-10},"shapeId":"8aedf6c2-94e1-4506-89d4-a0227c552f1e","xaxis":1,"zaxis":3},{"bounds":{"x":16,"y":1,"z":1},"color":"675f51","pos":{"x":-8,"y":13,"z":2},"shapeId":"8aedf6c2-94e1-4506-89d4-a0227c552f1e","xaxis":1,"zaxis":3},{"bounds":{"x":1,"y":16,"z":1},"color":"675f51","pos":{"x":-8,"y":-3,"z":2},"shapeId":"8aedf6c2-94e1-4506-89d4-a0227c552f1e","xaxis":1,"zaxis":3},{"bounds":{"x":16,"y":1,"z":1},"color":"675f51","pos":{"x":-8,"y":-4,"z":2},"shapeId":"8aedf6c2-94e1-4506-89d4-a0227c552f1e","xaxis":1,"zaxis":3},{"bounds":{"x":1,"y":14,"z":1},"color":"675f51","pos":{"x":9,"y":-2,"z":2},"shapeId":"8aedf6c2-94e1-4506-89d4-a0227c552f1e","xaxis":1,"zaxis":3},{"bounds":{"x":1,"y":1,"z":1},"color":"675f51","pos":{"x":9,"y":13,"z":2},"shapeId":"8aedf6c2-94e1-4506-89d4-a0227c552f1e","xaxis":1,"zaxis":3},{"bounds":{"x":16,"y":16,"z":1},"color":"675f51","pos":{"x":-7,"y":-3,"z":-10},"shapeId":"8aedf6c2-94e1-4506-89d4-a0227c552f1e","xaxis":1,"zaxis":3},{"bounds":{"x":1,"y":1,"z":1},"color":"675f51","pos":{"x":-8,"y":-4,"z":1},"shapeId":"8aedf6c2-94e1-4506-89d4-a0227c552f1e","xaxis":1,"zaxis":3},{"color":"eeeeee","controller":{"containers":null,"controllers":[{"id":1902}],"id":1905,"joints":null},"pos":{"x":8,"y":-3,"z":3},"shapeId":"1742f96c-e3b7-408f-8291-06a125e87355","xaxis":2,"zaxis":-3},{"color":"222222","controller":{"active":false,"controllers":[{"id":1898},{"id":1896}],"id":1904,"joints":null,"mode":0},"pos":{"x":8,"y":-3,"z":4},"shapeId":"9f0f56e8-2c31-4d83-996c-d00a9b296c3f","xaxis":2,"zaxis":-3},{"color":"7eeded","controller":{"containers":null,"controllers":[{"id":1902},{"id":1896}],"data":"gExVQQAAAAEFBQDQAgAAAAKAc3RhdGUIAA","id":1903,"joints":null},"pos":{"x":8,"y":-2,"z":9},"shapeId":"bbd2a902-de99-459e-89cd-3c84de790775","xaxis":-2,"zaxis":3},{"color":"df7f01","controller":{"active":false,"controllers":[{"id":1901}],"id":1902,"joints":null,"mode":2},"pos":{"x":8,"y":-2,"z":8},"shapeId":"9f0f56e8-2c31-4d83-996c-d00a9b296c3f","xaxis":-2,"zaxis":3},{"color":"d02525","controller":{"active":false,"controllers":[{"id":1903}],"id":1901,"joints":null,"mode":0},"pos":{"x":8,"y":-2,"z":7},"shapeId":"9f0f56e8-2c31-4d83-996c-d00a9b296c3f","xaxis":-2,"zaxis":3},{"color":"0a3ee2","controller":{"active":false,"controllers":[{"id":1901}],"id":1900,"joints":null,"mode":0},"pos":{"x":8,"y":-2,"z":6},"shapeId":"9f0f56e8-2c31-4d83-996c-d00a9b296c3f","xaxis":-2,"zaxis":3},{"color":"f06767","controller":{"containers":null,"controllers":[{"id":1898}],"id":1899,"joints":null},"pos":{"x":9,"y":-3,"z":6},"shapeId":"1742f96c-e3b7-408f-8291-06a125e87355","xaxis":2,"zaxis":-1},{"color":"f06767","controller":{"active":false,"controllers":[{"id":1900}],"id":1898,"joints":null,"mode":0},"pos":{"x":8,"y":-3,"z":5},"shapeId":"9f0f56e8-2c31-4d83-996c-d00a9b296c3f","xaxis":2,"zaxis":-3},{"color":"eeaf5c","controller":{"containers":null,"controllers":[{"id":1896}],"id":1897,"joints":null},"pos":{"x":8,"y":-2,"z":10},"shapeId":"1742f96c-e3b7-408f-8291-06a125e87355","xaxis":-2,"zaxis":3},{"color":"35086c","controller":{"active":false,"controllers":[{"id":1895}],"id":1896,"joints":null,"mode":0},"pos":{"x":8,"y":-2,"z":11},"shapeId":"9f0f56e8-2c31-4d83-996c-d00a9b296c3f","xaxis":-2,"zaxis":3},{"color":"7eeded","controller":{"containers":null,"controllers":null,"id":1895,"joints":null},"pos":{"x":8,"y":-2,"z":12},"shapeId":"b66bf85d-5bee-4461-bee3-b83f371faf04","xaxis":-2,"zaxis":3},{"bounds":{"x":1,"y":1,"z":13},"color":"675f51","pos":{"x":9,"y":-3,"z":-10},"shapeId":"8aedf6c2-94e1-4506-89d4-a0227c552f1e","xaxis":1,"zaxis":3},{"color":"222222","controller":{"active":false,"controllers":[{"id":1887},{"id":1885}],"id":1893,"joints":null,"mode":0},"pos":{"x":8,"y":-2,"z":4},"shapeId":"9f0f56e8-2c31-4d83-996c-d00a9b296c3f","xaxis":2,"zaxis":-3},{"color":"7eeded","controller":{"containers":null,"controllers":[{"id":1891},{"id":1885}],"data":"gExVQQAAAAEFBQDQAgAAAAKAc3RhdGUIAA","id":1892,"joints":null},"pos":{"x":8,"y":-1,"z":9},"shapeId":"bbd2a902-de99-459e-89cd-3c84de790775","xaxis":-2,"zaxis":3},{"color":"df7f01","controller":{"active":false,"controllers":[{"id":1890}],"id":1891,"joints":null,"mode":2},"pos":{"x":8,"y":-1,"z":8},"shapeId":"9f0f56e8-2c31-4d83-996c-d00a9b296c3f","xaxis":-2,"zaxis":3},{"color":"d02525","controller":{"active":false,"controllers":[{"id":1892}],"id":1890,"joints":null,"mode":0},"pos":{"x":8,"y":-1,"z":7},"shapeId":"9f0f56e8-2c31-4d83-996c-d00a9b296c3f","xaxis":-2,"zaxis":3},{"color":"0a3ee2","controller":{"active":false,"controllers":[{"id":1890}],"id":1889,"joints":null,"mode":0},"pos":{"x":8,"y":-1,"z":6},"shapeId":"9f0f56e8-2c31-4d83-996c-d00a9b296c3f","xaxis":-2,"zaxis":3},{"color":"f06767","controller":{"containers":null,"controllers":[{"id":1887}],"id":1888,"joints":null},"pos":{"x":9,"y":-2,"z":6},"shapeId":"1742f96c-e3b7-408f-8291-06a125e87355","xaxis":2,"zaxis":-1},{"color":"f06767","controller":{"active":false,"controllers":[{"id":1889}],"id":1887,"joints":null,"mode":0},"pos":{"x":8,"y":-2,"z":5},"shapeId":"9f0f56e8-2c31-4d83-996c-d00a9b296c3f","xaxis":2,"zaxis":-3},{"color":"eeaf5c","controller":{"containers":null,"controllers":[{"id":1885}],"id":1886,"joints":null},"pos":{"x":8,"y":-1,"z":10},"shapeId":"1742f96c-e3b7-408f-8291-06a125e87355","xaxis":-2,"zaxis":3},{"color":"35086c","controller":{"active":false,"controllers":[{"id":1884}],"id":1885,"joints":null,"mode":0},"pos":{"x":8,"y":-1,"z":11},"shapeId":"9f0f56e8-2c31-4d83-996c-d00a9b296c3f","xaxis":-2,"zaxis":3},{"color":"7eeded","controller":{"containers":null,"controllers":null,"id":1884,"joints":null},"pos":{"x":8,"y":-1,"z":12},"shapeId":"b66bf85d-5bee-4461-bee3-b83f371faf04","xaxis":-2,"zaxis":3},{"color":"eeeeee","controller":{"containers":null,"controllers":[{"id":1891}],"id":1894,"joints":null},"pos":{"x":8,"y":-2,"z":3},"shapeId":"1742f96c-e3b7-408f-8291-06a125e87355","xaxis":2,"zaxis":-3},{"color":"222222","controller":{"active":false,"controllers":[{"id":1876},{"id":1874}],"id":1882,"joints":null,"mode":0},"pos":{"x":8,"y":-1,"z":4},"shapeId":"9f0f56e8-2c31-4d83-996c-d00a9b296c3f","xaxis":2,"zaxis":-3},{"color":"7eeded","controller":{"containers":null,"controllers":[{"id":1880},{"id":1874}],"data":"gExVQQAAAAEFBQDQAgAAAAKAc3RhdGUIAA","id":1881,"joints":null},"pos":{"x":8,"y":0,"z":9},"shapeId":"bbd2a902-de99-459e-89cd-3c84de790775","xaxis":-2,"zaxis":3},{"color":"df7f01","controller":{"active":false,"controllers":[{"id":1879}],"id":1880,"joints":null,"mode":2},"pos":{"x":8,"y":0,"z":8},"shapeId":"9f0f56e8-2c31-4d83-996c-d00a9b296c3f","xaxis":-2,"zaxis":3},{"color":"d02525","controller":{"active":false,"controllers":[{"id":1881}],"id":1879,"joints":null,"mode":0},"pos":{"x":8,"y":0,"z":7},"shapeId":"9f0f56e8-2c31-4d83-996c-d00a9b296c3f","xaxis":-2,"zaxis":3},{"color":"0a3ee2","controller":{"active":false,"controllers":[{"id":1879}],"id":1878,"joints":null,"mode":0},"pos":{"x":8,"y":0,"z":6},"shapeId":"9f0f56e8-2c31-4d83-996c-d00a9b296c3f","xaxis":-2,"zaxis":3},{"color":"f06767","controller":{"containers":null,"controllers":[{"id":1876}],"id":1877,"joints":null},"pos":{"x":9,"y":-1,"z":6},"shapeId":"1742f96c-e3b7-408f-8291-06a125e87355","xaxis":2,"zaxis":-1},{"color":"f06767","controller":{"active":false,"controllers":[{"id":1878}],"id":1876,"joints":null,"mode":0},"pos":{"x":8,"y":-1,"z":5},"shapeId":"9f0f56e8-2c31-4d83-996c-d00a9b296c3f","xaxis":2,"zaxis":-3},{"color":"eeaf5c","controller":{"containers":null,"controllers":[{"id":1874}],"id":1875,"joints":null},"pos":{"x":8,"y":0,"z":10},"shapeId":"1742f96c-e3b7-408f-8291-06a125e87355","xaxis":-2,"zaxis":3},{"color":"35086c","controller":{"active":false,"controllers":[{"id":1873}],"id":1874,"joints":null,"mode":0},"pos":{"x":8,"y":0,"z":11},"shapeId":"9f0f56e8-2c31-4d83-996c-d00a9b296c3f","xaxis":-2,"zaxis":3},{"color":"7eeded","controller":{"containers":null,"controllers":null,"id":1873,"joints":null},"pos":{"x":8,"y":0,"z":12},"shapeId":"b66bf85d-5bee-4461-bee3-b83f371faf04","xaxis":-2,"zaxis":3},{"color":"eeeeee","controller":{"containers":null,"controllers":[{"id":1880}],"id":1883,"joints":null},"pos":{"x":8,"y":-1,"z":3},"shapeId":"1742f96c-e3b7-408f-8291-06a125e87355","xaxis":2,"zaxis":-3},{"color":"222222","controller":{"active":false,"controllers":[{"id":1865},{"id":1863}],"id":1871,"joints":null,"mode":0},"pos":{"x":8,"y":0,"z":4},"shapeId":"9f0f56e8-2c31-4d83-996c-d00a9b296c3f","xaxis":2,"zaxis":-3},{"color":"7eeded","controller":{"containers":null,"controllers":[{"id":1869},{"id":1863}],"data":"gExVQQAAAAEFBQDQAgAAAAKAc3RhdGUIAA","id":1870,"joints":null},"pos":{"x":8,"y":1,"z":9},"shapeId":"bbd2a902-de99-459e-89cd-3c84de790775","xaxis":-2,"zaxis":3},{"color":"df7f01","controller":{"active":false,"controllers":[{"id":1868}],"id":1869,"joints":null,"mode":2},"pos":{"x":8,"y":1,"z":8},"shapeId":"9f0f56e8-2c31-4d83-996c-d00a9b296c3f","xaxis":-2,"zaxis":3},{"color":"d02525","controller":{"active":false,"controllers":[{"id":1870}],"id":1868,"joints":null,"mode":0},"pos":{"x":8,"y":1,"z":7},"shapeId":"9f0f56e8-2c31-4d83-996c-d00a9b296c3f","xaxis":-2,"zaxis":3},{"color":"0a3ee2","controller":{"active":false,"controllers":[{"id":1868}],"id":1867,"joints":null,"mode":0},"pos":{"x":8,"y":1,"z":6},"shapeId":"9f0f56e8-2c31-4d83-996c-d00a9b296c3f","xaxis":-2,"zaxis":3},{"color":"f06767","controller":{"containers":null,"controllers":[{"id":1865}],"id":1866,"joints":null},"pos":{"x":9,"y":0,"z":6},"shapeId":"1742f96c-e3b7-408f-8291-06a125e87355","xaxis":2,"zaxis":-1},{"color":"f06767","controller":{"active":false,"controllers":[{"id":1867}],"id":1865,"joints":null,"mode":0},"pos":{"x":8,"y":0,"z":5},"shapeId":"9f0f56e8-2c31-4d83-996c-d00a9b296c3f","xaxis":2,"zaxis":-3},{"color":"eeaf5c","controller":{"containers":null,"controllers":[{"id":1863}],"id":1864,"joints":null},"pos":{"x":8,"y":1,"z":10},"shapeId":"1742f96c-e3b7-408f-8291-06a125e87355","xaxis":-2,"zaxis":3},{"color":"35086c","controller":{"active":false,"controllers":[{"id":1862}],"id":1863,"joints":null,"mode":0},"pos":{"x":8,"y":1,"z":11},"shapeId":"9f0f56e8-2c31-4d83-996c-d00a9b296c3f","xaxis":-2,"zaxis":3},{"color":"7eeded","controller":{"containers":null,"controllers":null,"id":1862,"joints":null},"pos":{"x":8,"y":1,"z":12},"shapeId":"b66bf85d-5bee-4461-bee3-b83f371faf04","xaxis":-2,"zaxis":3},{"color":"eeeeee","controller":{"containers":null,"controllers":[{"id":1869}],"id":1872,"joints":null},"pos":{"x":8,"y":0,"z":3},"shapeId":"1742f96c-e3b7-408f-8291-06a125e87355","xaxis":2,"zaxis":-3},{"color":"222222","controller":{"active":false,"controllers":[{"id":1854},{"id":1852}],"id":1860,"joints":null,"mode":0},"pos":{"x":8,"y":1,"z":4},"shapeId":"9f0f56e8-2c31-4d83-996c-d00a9b296c3f","xaxis":2,"zaxis":-3},{"color":"7eeded","controller":{"containers":null,"controllers":[{"id":1858},{"id":1852}],"data":"gExVQQAAAAEFBQDQAgAAAAKAc3RhdGUIAA","id":1859,"joints":null},"pos":{"x":8,"y":2,"z":9},"shapeId":"bbd2a902-de99-459e-89cd-3c84de790775","xaxis":-2,"zaxis":3},{"color":"df7f01","controller":{"active":false,"controllers":[{"id":1857}],"id":1858,"joints":null,"mode":2},"pos":{"x":8,"y":2,"z":8},"shapeId":"9f0f56e8-2c31-4d83-996c-d00a9b296c3f","xaxis":-2,"zaxis":3},{"color":"d02525","controller":{"active":false,"controllers":[{"id":1859}],"id":1857,"joints":null,"mode":0},"pos":{"x":8,"y":2,"z":7},"shapeId":"9f0f56e8-2c31-4d83-996c-d00a9b296c3f","xaxis":-2,"zaxis":3},{"color":"0a3ee2","controller":{"active":false,"controllers":[{"id":1857}],"id":1856,"joints":null,"mode":0},"pos":{"x":8,"y":2,"z":6},"shapeId":"9f0f56e8-2c31-4d83-996c-d00a9b296c3f","xaxis":-2,"zaxis":3},{"color":"f06767","controller":{"containers":null,"controllers":[{"id":1854}],"id":1855,"joints":null},"pos":{"x":9,"y":1,"z":6},"shapeId":"1742f96c-e3b7-408f-8291-06a125e87355","xaxis":2,"zaxis":-1},{"color":"f06767","controller":{"active":false,"controllers":[{"id":1856}],"id":1854,"joints":null,"mode":0},"pos":{"x":8,"y":1,"z":5},"shapeId":"9f0f56e8-2c31-4d83-996c-d00a9b296c3f","xaxis":2,"zaxis":-3},{"color":"eeaf5c","controller":{"containers":null,"controllers":[{"id":1852}],"id":1853,"joints":null},"pos":{"x":8,"y":2,"z":10},"shapeId":"1742f96c-e3b7-408f-8291-06a125e87355","xaxis":-2,"zaxis":3},{"color":"35086c","controller":{"active":false,"controllers":[{"id":1851}],"id":1852,"joints":null,"mode":0},"pos":{"x":8,"y":2,"z":11},"shapeId":"9f0f56e8-2c31-4d83-996c-d00a9b296c3f","xaxis":-2,"zaxis":3},{"color":"7eeded","controller":{"containers":null,"controllers":null,"id":1851,"joints":null},"pos":{"x":8,"y":2,"z":12},"shapeId":"b66bf85d-5bee-4461-bee3-b83f371faf04","xaxis":-2,"zaxis":3},{"color":"eeeeee","controller":{"containers":null,"controllers":[{"id":1858}],"id":1861,"joints":null},"pos":{"x":8,"y":1,"z":3},"shapeId":"1742f96c-e3b7-408f-8291-06a125e87355","xaxis":2,"zaxis":-3},{"color":"222222","controller":{"active":false,"controllers":[{"id":1843},{"id":1841}],"id":1849,"joints":null,"mode":0},"pos":{"x":8,"y":2,"z":4},"shapeId":"9f0f56e8-2c31-4d83-996c-d00a9b296c3f","xaxis":2,"zaxis":-3},{"color":"7eeded","controller":{"containers":null,"controllers":[{"id":1847},{"id":1841}],"data":"gExVQQAAAAEFBQDQAgAAAAKAc3RhdGUIAA","id":1848,"joints":null},"pos":{"x":8,"y":3,"z":9},"shapeId":"bbd2a902-de99-459e-89cd-3c84de790775","xaxis":-2,"zaxis":3},{"color":"df7f01","controller":{"active":false,"controllers":[{"id":1846}],"id":1847,"joints":null,"mode":2},"pos":{"x":8,"y":3,"z":8},"shapeId":"9f0f56e8-2c31-4d83-996c-d00a9b296c3f","xaxis":-2,"zaxis":3},{"color":"d02525","controller":{"active":false,"controllers":[{"id":1848}],"id":1846,"joints":null,"mode":0},"pos":{"x":8,"y":3,"z":7},"shapeId":"9f0f56e8-2c31-4d83-996c-d00a9b296c3f","xaxis":-2,"zaxis":3},{"color":"0a3ee2","controller":{"active":false,"controllers":[{"id":1846}],"id":1845,"joints":null,"mode":0},"pos":{"x":8,"y":3,"z":6},"shapeId":"9f0f56e8-2c31-4d83-996c-d00a9b296c3f","xaxis":-2,"zaxis":3},{"color":"f06767","controller":{"containers":null,"controllers":[{"id":1843}],"id":1844,"joints":null},"pos":{"x":9,"y":2,"z":6},"shapeId":"1742f96c-e3b7-408f-8291-06a125e87355","xaxis":2,"zaxis":-1},{"color":"f06767","controller":{"active":false,"controllers":[{"id":1845}],"id":1843,"joints":null,"mode":0},"pos":{"x":8,"y":2,"z":5},"shapeId":"9f0f56e8-2c31-4d83-996c-d00a9b296c3f","xaxis":2,"zaxis":-3},{"color":"eeaf5c","controller":{"containers":null,"controllers":[{"id":1841}],"id":1842,"joints":null},"pos":{"x":8,"y":3,"z":10},"shapeId":"1742f96c-e3b7-408f-8291-06a125e87355","xaxis":-2,"zaxis":3},{"color":"35086c","controller":{"active":false,"controllers":[{"id":1840}],"id":1841,"joints":null,"mode":0},"pos":{"x":8,"y":3,"z":11},"shapeId":"9f0f56e8-2c31-4d83-996c-d00a9b296c3f","xaxis":-2,"zaxis":3},{"color":"7eeded","controller":{"containers":null,"controllers":null,"id":1840,"joints":null},"pos":{"x":8,"y":3,"z":12},"shapeId":"b66bf85d-5bee-4461-bee3-b83f371faf04","xaxis":-2,"zaxis":3},{"color":"eeeeee","controller":{"containers":null,"controllers":[{"id":1847}],"id":1850,"joints":null},"pos":{"x":8,"y":2,"z":3},"shapeId":"1742f96c-e3b7-408f-8291-06a125e87355","xaxis":2,"zaxis":-3},{"color":"222222","controller":{"active":false,"controllers":[{"id":1832},{"id":1830}],"id":1838,"joints":null,"mode":0},"pos":{"x":8,"y":3,"z":4},"shapeId":"9f0f56e8-2c31-4d83-996c-d00a9b296c3f","xaxis":2,"zaxis":-3},{"color":"7eeded","controller":{"containers":null,"controllers":[{"id":1836},{"id":1830}],"data":"gExVQQAAAAEFBQDQAgAAAAKAc3RhdGUIAA","id":1837,"joints":null},"pos":{"x":8,"y":4,"z":9},"shapeId":"bbd2a902-de99-459e-89cd-3c84de790775","xaxis":-2,"zaxis":3},{"color":"df7f01","controller":{"active":false,"controllers":[{"id":1835}],"id":1836,"joints":null,"mode":2},"pos":{"x":8,"y":4,"z":8},"shapeId":"9f0f56e8-2c31-4d83-996c-d00a9b296c3f","xaxis":-2,"zaxis":3},{"color":"d02525","controller":{"active":false,"controllers":[{"id":1837}],"id":1835,"joints":null,"mode":0},"pos":{"x":8,"y":4,"z":7},"shapeId":"9f0f56e8-2c31-4d83-996c-d00a9b296c3f","xaxis":-2,"zaxis":3},{"color":"0a3ee2","controller":{"active":false,"controllers":[{"id":1835}],"id":1834,"joints":null,"mode":0},"pos":{"x":8,"y":4,"z":6},"shapeId":"9f0f56e8-2c31-4d83-996c-d00a9b296c3f","xaxis":-2,"zaxis":3},{"color":"f06767","controller":{"containers":null,"controllers":[{"id":1832}],"id":1833,"joints":null},"pos":{"x":9,"y":3,"z":6},"shapeId":"1742f96c-e3b7-408f-8291-06a125e87355","xaxis":2,"zaxis":-1},{"color":"f06767","controller":{"active":false,"controllers":[{"id":1834}],"id":1832,"joints":null,"mode":0},"pos":{"x":8,"y":3,"z":5},"shapeId":"9f0f56e8-2c31-4d83-996c-d00a9b296c3f","xaxis":2,"zaxis":-3},{"color":"eeaf5c","controller":{"containers":null,"controllers":[{"id":1830}],"id":1831,"joints":null},"pos":{"x":8,"y":4,"z":10},"shapeId":"1742f96c-e3b7-408f-8291-06a125e87355","xaxis":-2,"zaxis":3},{"color":"35086c","controller":{"active":false,"controllers":[{"id":1829}],"id":1830,"joints":null,"mode":0},"pos":{"x":8,"y":4,"z":11},"shapeId":"9f0f56e8-2c31-4d83-996c-d00a9b296c3f","xaxis":-2,"zaxis":3},{"color":"7eeded","controller":{"containers":null,"controllers":null,"id":1829,"joints":null},"pos":{"x":8,"y":4,"z":12},"shapeId":"b66bf85d-5bee-4461-bee3-b83f371faf04","xaxis":-2,"zaxis":3},{"color":"eeeeee","controller":{"containers":null,"controllers":[{"id":1836}],"id":1839,"joints":null},"pos":{"x":8,"y":3,"z":3},"shapeId":"1742f96c-e3b7-408f-8291-06a125e87355","xaxis":2,"zaxis":-3},{"color":"222222","controller":{"active":false,"controllers":[{"id":1821},{"id":1819}],"id":1827,"joints":null,"mode":0},"pos":{"x":8,"y":4,"z":4},"shapeId":"9f0f56e8-2c31-4d83-996c-d00a9b296c3f","xaxis":2,"zaxis":-3},{"color":"7eeded","controller":{"containers":null,"controllers":[{"id":1825},{"id":1819}],"data":"gExVQQAAAAEFBQDQAgAAAAKAc3RhdGUIAA","id":1826,"joints":null},"pos":{"x":8,"y":5,"z":9},"shapeId":"bbd2a902-de99-459e-89cd-3c84de790775","xaxis":-2,"zaxis":3},{"color":"df7f01","controller":{"active":false,"controllers":[{"id":1824}],"id":1825,"joints":null,"mode":2},"pos":{"x":8,"y":5,"z":8},"shapeId":"9f0f56e8-2c31-4d83-996c-d00a9b296c3f","xaxis":-2,"zaxis":3},{"color":"d02525","controller":{"active":false,"controllers":[{"id":1826}],"id":1824,"joints":null,"mode":0},"pos":{"x":8,"y":5,"z":7},"shapeId":"9f0f56e8-2c31-4d83-996c-d00a9b296c3f","xaxis":-2,"zaxis":3},{"color":"0a3ee2","controller":{"active":false,"controllers":[{"id":1824}],"id":1823,"joints":null,"mode":0},"pos":{"x":8,"y":5,"z":6},"shapeId":"9f0f56e8-2c31-4d83-996c-d00a9b296c3f","xaxis":-2,"zaxis":3},{"color":"f06767","controller":{"containers":null,"controllers":[{"id":1821}],"id":1822,"joints":null},"pos":{"x":9,"y":4,"z":6},"shapeId":"1742f96c-e3b7-408f-8291-06a125e87355","xaxis":2,"zaxis":-1},{"color":"f06767","controller":{"active":false,"controllers":[{"id":1823}],"id":1821,"joints":null,"mode":0},"pos":{"x":8,"y":4,"z":5},"shapeId":"9f0f56e8-2c31-4d83-996c-d00a9b296c3f","xaxis":2,"zaxis":-3},{"color":"eeaf5c","controller":{"containers":null,"controllers":[{"id":1819}],"id":1820,"joints":null},"pos":{"x":8,"y":5,"z":10},"shapeId":"1742f96c-e3b7-408f-8291-06a125e87355","xaxis":-2,"zaxis":3},{"color":"35086c","controller":{"active":false,"controllers":[{"id":1818}],"id":1819,"joints":null,"mode":0},"pos":{"x":8,"y":5,"z":11},"shapeId":"9f0f56e8-2c31-4d83-996c-d00a9b296c3f","xaxis":-2,"zaxis":3},{"color":"7eeded","controller":{"containers":null,"controllers":null,"id":1818,"joints":null},"pos":{"x":8,"y":5,"z":12},"shapeId":"b66bf85d-5bee-4461-bee3-b83f371faf04","xaxis":-2,"zaxis":3},{"color":"eeeeee","controller":{"containers":null,"controllers":[{"id":1825}],"id":1828,"joints":null},"pos":{"x":8,"y":4,"z":3},"shapeId":"1742f96c-e3b7-408f-8291-06a125e87355","xaxis":2,"zaxis":-3},{"color":"222222","controller":{"active":false,"controllers":[{"id":1810},{"id":1808}],"id":1816,"joints":null,"mode":0},"pos":{"x":8,"y":5,"z":4},"shapeId":"9f0f56e8-2c31-4d83-996c-d00a9b296c3f","xaxis":2,"zaxis":-3},{"color":"7eeded","controller":{"containers":null,"controllers":[{"id":1814},{"id":1808}],"data":"gExVQQAAAAEFBQDQAgAAAAKAc3RhdGUIAA","id":1815,"joints":null},"pos":{"x":8,"y":6,"z":9},"shapeId":"bbd2a902-de99-459e-89cd-3c84de790775","xaxis":-2,"zaxis":3},{"color":"df7f01","controller":{"active":false,"controllers":[{"id":1813}],"id":1814,"joints":null,"mode":2},"pos":{"x":8,"y":6,"z":8},"shapeId":"9f0f56e8-2c31-4d83-996c-d00a9b296c3f","xaxis":-2,"zaxis":3},{"color":"d02525","controller":{"active":false,"controllers":[{"id":1815}],"id":1813,"joints":null,"mode":0},"pos":{"x":8,"y":6,"z":7},"shapeId":"9f0f56e8-2c31-4d83-996c-d00a9b296c3f","xaxis":-2,"zaxis":3},{"color":"0a3ee2","controller":{"active":false,"controllers":[{"id":1813}],"id":1812,"joints":null,"mode":0},"pos":{"x":8,"y":6,"z":6},"shapeId":"9f0f56e8-2c31-4d83-996c-d00a9b296c3f","xaxis":-2,"zaxis":3},{"color":"f06767","controller":{"containers":null,"controllers":[{"id":1810}],"id":1811,"joints":null},"pos":{"x":9,"y":5,"z":6},"shapeId":"1742f96c-e3b7-408f-8291-06a125e87355","xaxis":2,"zaxis":-1},{"color":"f06767","controller":{"active":false,"controllers":[{"id":1812}],"id":1810,"joints":null,"mode":0},"pos":{"x":8,"y":5,"z":5},"shapeId":"9f0f56e8-2c31-4d83-996c-d00a9b296c3f","xaxis":2,"zaxis":-3},{"color":"eeaf5c","controller":{"containers":null,"controllers":[{"id":1808}],"id":1809,"joints":null},"pos":{"x":8,"y":6,"z":10},"shapeId":"1742f96c-e3b7-408f-8291-06a125e87355","xaxis":-2,"zaxis":3},{"color":"35086c","controller":{"active":false,"controllers":[{"id":1807}],"id":1808,"joints":null,"mode":0},"pos":{"x":8,"y":6,"z":11},"shapeId":"9f0f56e8-2c31-4d83-996c-d00a9b296c3f","xaxis":-2,"zaxis":3},{"color":"7eeded","controller":{"containers":null,"controllers":null,"id":1807,"joints":null},"pos":{"x":8,"y":6,"z":12},"shapeId":"b66bf85d-5bee-4461-bee3-b83f371faf04","xaxis":-2,"zaxis":3},{"color":"eeeeee","controller":{"containers":null,"controllers":[{"id":1814}],"id":1817,"joints":null},"pos":{"x":8,"y":5,"z":3},"shapeId":"1742f96c-e3b7-408f-8291-06a125e87355","xaxis":2,"zaxis":-3},{"color":"222222","controller":{"active":false,"controllers":[{"id":1799},{"id":1797}],"id":1805,"joints":null,"mode":0},"pos":{"x":8,"y":6,"z":4},"shapeId":"9f0f56e8-2c31-4d83-996c-d00a9b296c3f","xaxis":2,"zaxis":-3},{"color":"7eeded","controller":{"containers":null,"controllers":[{"id":1803},{"id":1797}],"data":"gExVQQAAAAEFBQDQAgAAAAKAc3RhdGUIAA","id":1804,"joints":null},"pos":{"x":8,"y":7,"z":9},"shapeId":"bbd2a902-de99-459e-89cd-3c84de790775","xaxis":-2,"zaxis":3},{"color":"df7f01","controller":{"active":false,"controllers":[{"id":1802}],"id":1803,"joints":null,"mode":2},"pos":{"x":8,"y":7,"z":8},"shapeId":"9f0f56e8-2c31-4d83-996c-d00a9b296c3f","xaxis":-2,"zaxis":3},{"color":"d02525","controller":{"active":false,"controllers":[{"id":1804}],"id":1802,"joints":null,"mode":0},"pos":{"x":8,"y":7,"z":7},"shapeId":"9f0f56e8-2c31-4d83-996c-d00a9b296c3f","xaxis":-2,"zaxis":3},{"color":"0a3ee2","controller":{"active":false,"controllers":[{"id":1802}],"id":1801,"joints":null,"mode":0},"pos":{"x":8,"y":7,"z":6},"shapeId":"9f0f56e8-2c31-4d83-996c-d00a9b296c3f","xaxis":-2,"zaxis":3},{"color":"f06767","controller":{"containers":null,"controllers":[{"id":1799}],"id":1800,"joints":null},"pos":{"x":9,"y":6,"z":6},"shapeId":"1742f96c-e3b7-408f-8291-06a125e87355","xaxis":2,"zaxis":-1},{"color":"f06767","controller":{"active":false,"controllers":[{"id":1801}],"id":1799,"joints":null,"mode":0},"pos":{"x":8,"y":6,"z":5},"shapeId":"9f0f56e8-2c31-4d83-996c-d00a9b296c3f","xaxis":2,"zaxis":-3},{"color":"eeaf5c","controller":{"containers":null,"controllers":[{"id":1797}],"id":1798,"joints":null},"pos":{"x":8,"y":7,"z":10},"shapeId":"1742f96c-e3b7-408f-8291-06a125e87355","xaxis":-2,"zaxis":3},{"color":"35086c","controller":{"active":false,"controllers":[{"id":1796}],"id":1797,"joints":null,"mode":0},"pos":{"x":8,"y":7,"z":11},"shapeId":"9f0f56e8-2c31-4d83-996c-d00a9b296c3f","xaxis":-2,"zaxis":3},{"color":"7eeded","controller":{"containers":null,"controllers":null,"id":1796,"joints":null},"pos":{"x":8,"y":7,"z":12},"shapeId":"b66bf85d-5bee-4461-bee3-b83f371faf04","xaxis":-2,"zaxis":3},{"color":"eeeeee","controller":{"containers":null,"controllers":[{"id":1803}],"id":1806,"joints":null},"pos":{"x":8,"y":6,"z":3},"shapeId":"1742f96c-e3b7-408f-8291-06a125e87355","xaxis":2,"zaxis":-3},{"color":"222222","controller":{"active":false,"controllers":[{"id":1788},{"id":1786}],"id":1794,"joints":null,"mode":0},"pos":{"x":8,"y":7,"z":4},"shapeId":"9f0f56e8-2c31-4d83-996c-d00a9b296c3f","xaxis":2,"zaxis":-3},{"color":"7eeded","controller":{"containers":null,"controllers":[{"id":1792},{"id":1786}],"data":"gExVQQAAAAEFBQDQAgAAAAKAc3RhdGUIAA","id":1793,"joints":null},"pos":{"x":8,"y":8,"z":9},"shapeId":"bbd2a902-de99-459e-89cd-3c84de790775","xaxis":-2,"zaxis":3},{"color":"df7f01","controller":{"active":false,"controllers":[{"id":1791}],"id":1792,"joints":null,"mode":2},"pos":{"x":8,"y":8,"z":8},"shapeId":"9f0f56e8-2c31-4d83-996c-d00a9b296c3f","xaxis":-2,"zaxis":3},{"color":"d02525","controller":{"active":false,"controllers":[{"id":1793}],"id":1791,"joints":null,"mode":0},"pos":{"x":8,"y":8,"z":7},"shapeId":"9f0f56e8-2c31-4d83-996c-d00a9b296c3f","xaxis":-2,"zaxis":3},{"color":"0a3ee2","controller":{"active":false,"controllers":[{"id":1791}],"id":1790,"joints":null,"mode":0},"pos":{"x":8,"y":8,"z":6},"shapeId":"9f0f56e8-2c31-4d83-996c-d00a9b296c3f","xaxis":-2,"zaxis":3},{"color":"f06767","controller":{"containers":null,"controllers":[{"id":1788}],"id":1789,"joints":null},"pos":{"x":9,"y":7,"z":6},"shapeId":"1742f96c-e3b7-408f-8291-06a125e87355","xaxis":2,"zaxis":-1},{"color":"f06767","controller":{"active":false,"controllers":[{"id":1790}],"id":1788,"joints":null,"mode":0},"pos":{"x":8,"y":7,"z":5},"shapeId":"9f0f56e8-2c31-4d83-996c-d00a9b296c3f","xaxis":2,"zaxis":-3},{"color":"eeaf5c","controller":{"containers":null,"controllers":[{"id":1786}],"id":1787,"joints":null},"pos":{"x":8,"y":8,"z":10},"shapeId":"1742f96c-e3b7-408f-8291-06a125e87355","xaxis":-2,"zaxis":3},{"color":"35086c","controller":{"active":false,"controllers":[{"id":1785}],"id":1786,"joints":null,"mode":0},"pos":{"x":8,"y":8,"z":11},"shapeId":"9f0f56e8-2c31-4d83-996c-d00a9b296c3f","xaxis":-2,"zaxis":3},{"color":"7eeded","controller":{"containers":null,"controllers":null,"id":1785,"joints":null},"pos":{"x":8,"y":8,"z":12},"shapeId":"b66bf85d-5bee-4461-bee3-b83f371faf04","xaxis":-2,"zaxis":3},{"color":"eeeeee","controller":{"containers":null,"controllers":[{"id":1792}],"id":1795,"joints":null},"pos":{"x":8,"y":7,"z":3},"shapeId":"1742f96c-e3b7-408f-8291-06a125e87355","xaxis":2,"zaxis":-3},{"color":"222222","controller":{"active":false,"controllers":[{"id":1777},{"id":1775}],"id":1783,"joints":null,"mode":0},"pos":{"x":8,"y":8,"z":4},"shapeId":"9f0f56e8-2c31-4d83-996c-d00a9b296c3f","xaxis":2,"zaxis":-3},{"color":"7eeded","controller":{"containers":null,"controllers":[{"id":1781},{"id":1775}],"data":"gExVQQAAAAEFBQDQAgAAAAKAc3RhdGUIAA","id":1782,"joints":null},"pos":{"x":8,"y":9,"z":9},"shapeId":"bbd2a902-de99-459e-89cd-3c84de790775","xaxis":-2,"zaxis":3},{"color":"df7f01","controller":{"active":false,"controllers":[{"id":1780}],"id":1781,"joints":null,"mode":2},"pos":{"x":8,"y":9,"z":8},"shapeId":"9f0f56e8-2c31-4d83-996c-d00a9b296c3f","xaxis":-2,"zaxis":3},{"color":"d02525","controller":{"active":false,"controllers":[{"id":1782}],"id":1780,"joints":null,"mode":0},"pos":{"x":8,"y":9,"z":7},"shapeId":"9f0f56e8-2c31-4d83-996c-d00a9b296c3f","xaxis":-2,"zaxis":3},{"color":"0a3ee2","controller":{"active":false,"controllers":[{"id":1780}],"id":1779,"joints":null,"mode":0},"pos":{"x":8,"y":9,"z":6},"shapeId":"9f0f56e8-2c31-4d83-996c-d00a9b296c3f","xaxis":-2,"zaxis":3},{"color":"f06767","controller":{"containers":null,"controllers":[{"id":1777}],"id":1778,"joints":null},"pos":{"x":9,"y":8,"z":6},"shapeId":"1742f96c-e3b7-408f-8291-06a125e87355","xaxis":2,"zaxis":-1},{"color":"f06767","controller":{"active":false,"controllers":[{"id":1779}],"id":1777,"joints":null,"mode":0},"pos":{"x":8,"y":8,"z":5},"shapeId":"9f0f56e8-2c31-4d83-996c-d00a9b296c3f","xaxis":2,"zaxis":-3},{"color":"eeaf5c","controller":{"containers":null,"controllers":[{"id":1775}],"id":1776,"joints":null},"pos":{"x":8,"y":9,"z":10},"shapeId":"1742f96c-e3b7-408f-8291-06a125e87355","xaxis":-2,"zaxis":3},{"color":"35086c","controller":{"active":false,"controllers":[{"id":1774}],"id":1775,"joints":null,"mode":0},"pos":{"x":8,"y":9,"z":11},"shapeId":"9f0f56e8-2c31-4d83-996c-d00a9b296c3f","xaxis":-2,"zaxis":3},{"color":"7eeded","controller":{"containers":null,"controllers":null,"id":1774,"joints":null},"pos":{"x":8,"y":9,"z":12},"shapeId":"b66bf85d-5bee-4461-bee3-b83f371faf04","xaxis":-2,"zaxis":3},{"color":"eeeeee","controller":{"containers":null,"controllers":[{"id":1781}],"id":1784,"joints":null},"pos":{"x":8,"y":8,"z":3},"shapeId":"1742f96c-e3b7-408f-8291-06a125e87355","xaxis":2,"zaxis":-3},{"color":"222222","controller":{"active":false,"controllers":[{"id":1766},{"id":1764}],"id":1772,"joints":null,"mode":0},"pos":{"x":8,"y":9,"z":4},"shapeId":"9f0f56e8-2c31-4d83-996c-d00a9b296c3f","xaxis":2,"zaxis":-3},{"color":"7eeded","controller":{"containers":null,"controllers":[{"id":1770},{"id":1764}],"data":"gExVQQAAAAEFBQDQAgAAAAKAc3RhdGUIAA","id":1771,"joints":null},"pos":{"x":8,"y":10,"z":9},"shapeId":"bbd2a902-de99-459e-89cd-3c84de790775","xaxis":-2,"zaxis":3},{"color":"df7f01","controller":{"active":false,"controllers":[{"id":1769}],"id":1770,"joints":null,"mode":2},"pos":{"x":8,"y":10,"z":8},"shapeId":"9f0f56e8-2c31-4d83-996c-d00a9b296c3f","xaxis":-2,"zaxis":3},{"color":"d02525","controller":{"active":false,"controllers":[{"id":1771}],"id":1769,"joints":null,"mode":0},"pos":{"x":8,"y":10,"z":7},"shapeId":"9f0f56e8-2c31-4d83-996c-d00a9b296c3f","xaxis":-2,"zaxis":3},{"color":"0a3ee2","controller":{"active":false,"controllers":[{"id":1769}],"id":1768,"joints":null,"mode":0},"pos":{"x":8,"y":10,"z":6},"shapeId":"9f0f56e8-2c31-4d83-996c-d00a9b296c3f","xaxis":-2,"zaxis":3},{"color":"f06767","controller":{"containers":null,"controllers":[{"id":1766}],"id":1767,"joints":null},"pos":{"x":9,"y":9,"z":6},"shapeId":"1742f96c-e3b7-408f-8291-06a125e87355","xaxis":2,"zaxis":-1},{"color":"f06767","controller":{"active":false,"controllers":[{"id":1768}],"id":1766,"joints":null,"mode":0},"pos":{"x":8,"y":9,"z":5},"shapeId":"9f0f56e8-2c31-4d83-996c-d00a9b296c3f","xaxis":2,"zaxis":-3},{"color":"eeaf5c","controller":{"containers":null,"controllers":[{"id":1764}],"id":1765,"joints":null},"pos":{"x":8,"y":10,"z":10},"shapeId":"1742f96c-e3b7-408f-8291-06a125e87355","xaxis":-2,"zaxis":3},{"color":"35086c","controller":{"active":false,"controllers":[{"id":1763}],"id":1764,"joints":null,"mode":0},"pos":{"x":8,"y":10,"z":11},"shapeId":"9f0f56e8-2c31-4d83-996c-d00a9b296c3f","xaxis":-2,"zaxis":3},{"color":"7eeded","controller":{"containers":null,"controllers":null,"id":1763,"joints":null},"pos":{"x":8,"y":10,"z":12},"shapeId":"b66bf85d-5bee-4461-bee3-b83f371faf04","xaxis":-2,"zaxis":3},{"color":"eeeeee","controller":{"containers":null,"controllers":[{"id":1770}],"id":1773,"joints":null},"pos":{"x":8,"y":9,"z":3},"shapeId":"1742f96c-e3b7-408f-8291-06a125e87355","xaxis":2,"zaxis":-3},{"color":"222222","controller":{"active":false,"controllers":[{"id":1755},{"id":1753}],"id":1761,"joints":null,"mode":0},"pos":{"x":8,"y":10,"z":4},"shapeId":"9f0f56e8-2c31-4d83-996c-d00a9b296c3f","xaxis":2,"zaxis":-3},{"color":"7eeded","controller":{"containers":null,"controllers":[{"id":1759},{"id":1753}],"data":"gExVQQAAAAEFBQDQAgAAAAKAc3RhdGUIAA","id":1760,"joints":null},"pos":{"x":8,"y":11,"z":9},"shapeId":"bbd2a902-de99-459e-89cd-3c84de790775","xaxis":-2,"zaxis":3},{"color":"df7f01","controller":{"active":false,"controllers":[{"id":1758}],"id":1759,"joints":null,"mode":2},"pos":{"x":8,"y":11,"z":8},"shapeId":"9f0f56e8-2c31-4d83-996c-d00a9b296c3f","xaxis":-2,"zaxis":3},{"color":"d02525","controller":{"active":false,"controllers":[{"id":1760}],"id":1758,"joints":null,"mode":0},"pos":{"x":8,"y":11,"z":7},"shapeId":"9f0f56e8-2c31-4d83-996c-d00a9b296c3f","xaxis":-2,"zaxis":3},{"color":"0a3ee2","controller":{"active":false,"controllers":[{"id":1758}],"id":1757,"joints":null,"mode":0},"pos":{"x":8,"y":11,"z":6},"shapeId":"9f0f56e8-2c31-4d83-996c-d00a9b296c3f","xaxis":-2,"zaxis":3},{"color":"f06767","controller":{"containers":null,"controllers":[{"id":1755}],"id":1756,"joints":null},"pos":{"x":9,"y":10,"z":6},"shapeId":"1742f96c-e3b7-408f-8291-06a125e87355","xaxis":2,"zaxis":-1},{"color":"f06767","controller":{"active":false,"controllers":[{"id":1757}],"id":1755,"joints":null,"mode":0},"pos":{"x":8,"y":10,"z":5},"shapeId":"9f0f56e8-2c31-4d83-996c-d00a9b296c3f","xaxis":2,"zaxis":-3},{"color":"eeaf5c","controller":{"containers":null,"controllers":[{"id":1753}],"id":1754,"joints":null},"pos":{"x":8,"y":11,"z":10},"shapeId":"1742f96c-e3b7-408f-8291-06a125e87355","xaxis":-2,"zaxis":3},{"color":"35086c","controller":{"active":false,"controllers":[{"id":1752}],"id":1753,"joints":null,"mode":0},"pos":{"x":8,"y":11,"z":11},"shapeId":"9f0f56e8-2c31-4d83-996c-d00a9b296c3f","xaxis":-2,"zaxis":3},{"color":"7eeded","controller":{"containers":null,"controllers":null,"id":1752,"joints":null},"pos":{"x":8,"y":11,"z":12},"shapeId":"b66bf85d-5bee-4461-bee3-b83f371faf04","xaxis":-2,"zaxis":3},{"color":"eeeeee","controller":{"containers":null,"controllers":[{"id":1759}],"id":1762,"joints":null},"pos":{"x":8,"y":10,"z":3},"shapeId":"1742f96c-e3b7-408f-8291-06a125e87355","xaxis":2,"zaxis":-3},{"color":"222222","controller":{"active":false,"controllers":[{"id":1744},{"id":1742}],"id":1750,"joints":null,"mode":0},"pos":{"x":8,"y":11,"z":4},"shapeId":"9f0f56e8-2c31-4d83-996c-d00a9b296c3f","xaxis":2,"zaxis":-3},{"color":"7eeded","controller":{"containers":null,"controllers":[{"id":1748},{"id":1742}],"data":"gExVQQAAAAEFBQDQAgAAAAKAc3RhdGUIAA","id":1749,"joints":null},"pos":{"x":8,"y":12,"z":9},"shapeId":"bbd2a902-de99-459e-89cd-3c84de790775","xaxis":-2,"zaxis":3},{"color":"df7f01","controller":{"active":false,"controllers":[{"id":1747}],"id":1748,"joints":null,"mode":2},"pos":{"x":8,"y":12,"z":8},"shapeId":"9f0f56e8-2c31-4d83-996c-d00a9b296c3f","xaxis":-2,"zaxis":3},{"color":"d02525","controller":{"active":false,"controllers":[{"id":1749}],"id":1747,"joints":null,"mode":0},"pos":{"x":8,"y":12,"z":7},"shapeId":"9f0f56e8-2c31-4d83-996c-d00a9b296c3f","xaxis":-2,"zaxis":3},{"color":"0a3ee2","controller":{"active":false,"controllers":[{"id":1747}],"id":1746,"joints":null,"mode":0},"pos":{"x":8,"y":12,"z":6},"shapeId":"9f0f56e8-2c31-4d83-996c-d00a9b296c3f","xaxis":-2,"zaxis":3},{"color":"f06767","controller":{"containers":null,"controllers":[{"id":1744}],"id":1745,"joints":null},"pos":{"x":9,"y":11,"z":6},"shapeId":"1742f96c-e3b7-408f-8291-06a125e87355","xaxis":2,"zaxis":-1},{"color":"f06767","controller":{"active":false,"controllers":[{"id":1746}],"id":1744,"joints":null,"mode":0},"pos":{"x":8,"y":11,"z":5},"shapeId":"9f0f56e8-2c31-4d83-996c-d00a9b296c3f","xaxis":2,"zaxis":-3},{"color":"eeaf5c","controller":{"containers":null,"controllers":[{"id":1742}],"id":1743,"joints":null},"pos":{"x":8,"y":12,"z":10},"shapeId":"1742f96c-e3b7-408f-8291-06a125e87355","xaxis":-2,"zaxis":3},{"color":"35086c","controller":{"active":false,"controllers":[{"id":1741}],"id":1742,"joints":null,"mode":0},"pos":{"x":8,"y":12,"z":11},"shapeId":"9f0f56e8-2c31-4d83-996c-d00a9b296c3f","xaxis":-2,"zaxis":3},{"color":"7eeded","controller":{"containers":null,"controllers":null,"id":1741,"joints":null},"pos":{"x":8,"y":12,"z":12},"shapeId":"b66bf85d-5bee-4461-bee3-b83f371faf04","xaxis":-2,"zaxis":3},{"color":"eeeeee","controller":{"containers":null,"controllers":[{"id":1748}],"id":1751,"joints":null},"pos":{"x":8,"y":11,"z":3},"shapeId":"1742f96c-e3b7-408f-8291-06a125e87355","xaxis":2,"zaxis":-3},{"color":"7eeded","controller":{"containers":null,"controllers":null,"id":1634,"joints":null},"pos":{"x":8,"y":13,"z":12},"shapeId":"b66bf85d-5bee-4461-bee3-b83f371faf04","xaxis":-2,"zaxis":3},{"color":"35086c","controller":{"active":false,"controllers":[{"id":1634}],"id":1633,"joints":null,"mode":0},"pos":{"x":8,"y":13,"z":11},"shapeId":"9f0f56e8-2c31-4d83-996c-d00a9b296c3f","xaxis":-2,"zaxis":3},{"color":"eeaf5c","controller":{"containers":null,"controllers":[{"id":1633}],"id":1632,"joints":null},"pos":{"x":8,"y":13,"z":10},"shapeId":"1742f96c-e3b7-408f-8291-06a125e87355","xaxis":-2,"zaxis":3},{"color":"f06767","controller":{"active":false,"controllers":[{"id":1593}],"id":1661,"joints":null,"mode":0},"pos":{"x":8,"y":12,"z":5},"shapeId":"9f0f56e8-2c31-4d83-996c-d00a9b296c3f","xaxis":2,"zaxis":-3},{"color":"f06767","controller":{"containers":null,"controllers":[{"id":1661}],"id":1656,"joints":null},"pos":{"x":9,"y":12,"z":6},"shapeId":"1742f96c-e3b7-408f-8291-06a125e87355","xaxis":2,"zaxis":-1},{"color":"0a3ee2","controller":{"active":false,"controllers":[{"id":1595}],"id":1593,"joints":null,"mode":0},"pos":{"x":8,"y":13,"z":6},"shapeId":"9f0f56e8-2c31-4d83-996c-d00a9b296c3f","xaxis":-2,"zaxis":3},{"color":"d02525","controller":{"active":false,"controllers":[{"id":1598}],"id":1595,"joints":null,"mode":0},"pos":{"x":8,"y":13,"z":7},"shapeId":"9f0f56e8-2c31-4d83-996c-d00a9b296c3f","xaxis":-2,"zaxis":3},{"color":"df7f01","controller":{"active":false,"controllers":[{"id":1595}],"id":1596,"joints":null,"mode":2},"pos":{"x":8,"y":13,"z":8},"shapeId":"9f0f56e8-2c31-4d83-996c-d00a9b296c3f","xaxis":-2,"zaxis":3},{"color":"7eeded","controller":{"containers":null,"controllers":[{"id":1596},{"id":1633}],"data":"gExVQQAAAAEFBQDQAgAAAAKAc3RhdGUIAA","id":1598,"joints":null},"pos":{"x":8,"y":13,"z":9},"shapeId":"bbd2a902-de99-459e-89cd-3c84de790775","xaxis":-2,"zaxis":3},{"color":"222222","controller":{"active":false,"controllers":[{"id":1661},{"id":1633}],"id":1662,"joints":null,"mode":0},"pos":{"x":8,"y":12,"z":4},"shapeId":"9f0f56e8-2c31-4d83-996c-d00a9b296c3f","xaxis":2,"zaxis":-3},{"bounds":{"x":1,"y":1,"z":13},"color":"675f51","pos":{"x":9,"y":12,"z":-10},"shapeId":"8aedf6c2-94e1-4506-89d4-a0227c552f1e","xaxis":1,"zaxis":3},{"color":"eeeeee","controller":{"containers":null,"controllers":[{"id":1596}],"id":1663,"joints":null},"pos":{"x":8,"y":12,"z":3},"shapeId":"1742f96c-e3b7-408f-8291-06a125e87355","xaxis":2,"zaxis":-3},{"bounds":{"x":1,"y":1,"z":12},"color":"675f51","pos":{"x":-7,"y":13,"z":-10},"shapeId":"8aedf6c2-94e1-4506-89d4-a0227c552f1e","xaxis":1,"zaxis":3}]}],"version":3}
