{"bodies":[{"childs":[{"color":"df7f01","controller":{"active":true,"controllers":null,"id":2518,"joints":null,"mode":0},"pos":{"x":4,"y":1,"z":3},"shapeId":"9f0f56e8-2c31-4d83-996c-d00a9b296c3f","xaxis":1,"zaxis":-2},{"color":"df7f01","controller":{"active":false,"controllers":null,"id":2517,"joints":null,"mode":0},"pos":{"x":4,"y":2,"z":3},"shapeId":"9f0f56e8-2c31-4d83-996c-d00a9b296c3f","xaxis":1,"zaxis":-2},{"color":"df7f01","controller":{"active":false,"controllers":null,"id":2516,"joints":null,"mode":0},"pos":{"x":4,"y":3,"z":3},"shapeId":"9f0f56e8-2c31-4d83-996c-d00a9b296c3f","xaxis":1,"zaxis":-2},{"color":"df7f01","controller":{"active":false,"controllers":null,"id":2515,"joints":null,"mode":0},"pos":{"x":4,"y":4,"z":3},"shapeId":"9f0f56e8-2c31-4d83-996c-d00a9b296c3f","xaxis":1,"zaxis":-2},{"color":"df7f01","controller":{"active":false,"controllers":[{"id":2497},{"id":2492}],"id":2506,"joints":null,"mode":0},"pos":{"x":4,"y":6,"z":-1},"shapeId":"9f0f56e8-2c31-4d83-996c-d00a9b296c3f","xaxis":2,"zaxis":-3},{"color":"df7f01","controller":{"active":false,"controllers":[{"id":2496},{"id":2493}],"id":2505,"joints":null,"mode":0},"pos":{"x":4,"y":5,"z":-1},"shapeId":"9f0f56e8-2c31-4d83-996c-d00a9b296c3f","xaxis":2,"zaxis":-3},{"color":"df7f01","controller":{"active":false,"controllers":[{"id":2495},{"id":2494}],"id":2504,"joints":null,"mode":0},"pos":{"x":4,"y":4,"z":-1},"shapeId":"9f0f56e8-2c31-4d83-996c-d00a9b296c3f","xaxis":2,"zaxis":-3},{"color":"df7f01","controller":{"active":false,"controllers":[{"id":2501},{"id":2487}],"id":2510,"joints":null,"mode":0},"pos":{"x":4,"y":10,"z":-1},"shapeId":"9f0f56e8-2c31-4d83-996c-d00a9b296c3f","xaxis":2,"zaxis":-3},{"bounds":{"x":1,"y":16,"z":1},"color":"675f51","pos":{"x":4,"y":0,"z":-1},"shapeId":"8aedf6c2-94e1-4506-89d4-a0227c552f1e","xaxis":1,"zaxis":3},{"color":"df7f01","controller":{"active":false,"controllers":[{"id":2460},{"id":2517},{"id":2515},{"id":2452},{"id":2454},{"id":2457},{"id":2458},{"id":2462}],"id":2502,"joints":null,"mode":0},"pos":{"x":4,"y":15,"z":1},"shapeId":"9f0f56e8-2c31-4d83-996c-d00a9b296c3f","xaxis":2,"zaxis":-3},{"color":"df7f01","controller":{"active":false,"controllers":[{"id":2460},{"id":2461},{"id":2516},{"id":2515},{"id":2453},{"id":2454},{"id":2456},{"id":2458}],"id":2501,"joints":null,"mode":0},"pos":{"x":4,"y":12,"z":1},"shapeId":"9f0f56e8-2c31-4d83-996c-d00a9b296c3f","xaxis":2,"zaxis":-3},{"color":"df7f01","controller":{"active":false,"controllers":[{"id":2460},{"id":2461},{"id":2451},{"id":2452},{"id":2453},{"id":2454},{"id":2459},{"id":2462}],"id":2500,"joints":null,"mode":0},"pos":{"x":4,"y":9,"z":1},"shapeId":"9f0f56e8-2c31-4d83-996c-d00a9b296c3f","xaxis":2,"zaxis":-3},{"color":"df7f01","controller":{"active":false,"controllers":[{"id":2460},{"id":2461},{"id":2455},{"id":2457},{"id":2456},{"id":2458},{"id":2459},{"id":2462}],"id":2499,"joints":null,"mode":0},"pos":{"x":4,"y":6,"z":1},"shapeId":"9f0f56e8-2c31-4d83-996c-d00a9b296c3f","xaxis":2,"zaxis":-3},{"color":"df7f01","controller":{"active":false,"controllers":null,"id":2498,"joints":null,"mode":0},"pos":{"x":4,"y":3,"z":1},"shapeId":"9f0f56e8-2c31-4d83-996c-d00a9b296c3f","xaxis":2,"zaxis":-3},{"color":"df7f01","controller":{"active":false,"controllers":null,"id":2497,"joints":null,"mode":0},"pos":{"x":4,"y":2,"z":1},"shapeId":"9f0f56e8-2c31-4d83-996c-d00a9b296c3f","xaxis":2,"zaxis":-3},{"color":"df7f01","controller":{"active":false,"controllers":null,"id":2496,"joints":null,"mode":0},"pos":{"x":4,"y":1,"z":1},"shapeId":"9f0f56e8-2c31-4d83-996c-d00a9b296c3f","xaxis":2,"zaxis":-3},{"color":"df7f01","controller":{"active":false,"controllers":null,"id":2495,"joints":null,"mode":0},"pos":{"x":4,"y":0,"z":1},"shapeId":"9f0f56e8-2c31-4d83-996c-d00a9b296c3f","xaxis":2,"zaxis":-3},{"color":"df7f01","controller":{"active":true,"controllers":null,"id":2494,"joints":null,"mode":4},"pos":{"x":4,"y":0,"z":2},"shapeId":"9f0f56e8-2c31-4d83-996c-d00a9b296c3f","xaxis":2,"zaxis":-3},{"color":"df7f01","controller":{"active":true,"controllers":null,"id":2493,"joints":null,"mode":4},"pos":{"x":4,"y":1,"z":2},"shapeId":"9f0f56e8-2c31-4d83-996c-d00a9b296c3f","xaxis":2,"zaxis":-3},{"color":"df7f01","controller":{"active":true,"controllers":null,"id":2492,"joints":null,"mode":4},"pos":{"x":4,"y":2,"z":2},"shapeId":"9f0f56e8-2c31-4d83-996c-d00a9b296c3f","xaxis":2,"zaxis":-3},{"color":"df7f01","controller":{"active":true,"controllers":null,"id":2490,"joints":null,"mode":4},"pos":{"x":4,"y":3,"z":2},"shapeId":"9f0f56e8-2c31-4d83-996c-d00a9b296c3f","xaxis":2,"zaxis":-3},{"color":"df7f01","controller":{"active":true,"controllers":[{"id":2518},{"id":2517},{"id":2516},{"id":2515},{"id":2451},{"id":2452},{"id":2453},{"id":2454}],"id":2489,"joints":null,"mode":4},"pos":{"x":4,"y":6,"z":2},"shapeId":"9f0f56e8-2c31-4d83-996c-d00a9b296c3f","xaxis":2,"zaxis":-3},{"color":"df7f01","controller":{"active":true,"controllers":[{"id":2518},{"id":2517},{"id":2516},{"id":2515},{"id":2455},{"id":2457},{"id":2456},{"id":2458}],"id":2488,"joints":null,"mode":4},"pos":{"x":4,"y":9,"z":2},"shapeId":"9f0f56e8-2c31-4d83-996c-d00a9b296c3f","xaxis":2,"zaxis":-3},{"color":"df7f01","controller":{"active":true,"controllers":[{"id":2518},{"id":2517},{"id":2451},{"id":2452},{"id":2455},{"id":2457},{"id":2459},{"id":2462}],"id":2487,"joints":null,"mode":4},"pos":{"x":4,"y":12,"z":2},"shapeId":"9f0f56e8-2c31-4d83-996c-d00a9b296c3f","xaxis":2,"zaxis":-3},{"color":"df7f01","controller":{"active":true,"controllers":[{"id":2518},{"id":2461},{"id":2516},{"id":2451},{"id":2453},{"id":2455},{"id":2456},{"id":2459}],"id":2486,"joints":null,"mode":4},"pos":{"x":4,"y":15,"z":2},"shapeId":"9f0f56e8-2c31-4d83-996c-d00a9b296c3f","xaxis":2,"zaxis":-3},{"color":"df7f01","controller":{"active":false,"controllers":null,"id":2451,"joints":null,"mode":0},"pos":{"x":4,"y":5,"z":3},"shapeId":"9f0f56e8-2c31-4d83-996c-d00a9b296c3f","xaxis":1,"zaxis":-2},{"color":"df7f01","controller":{"active":false,"controllers":null,"id":2452,"joints":null,"mode":0},"pos":{"x":4,"y":6,"z":3},"shapeId":"9f0f56e8-2c31-4d83-996c-d00a9b296c3f","xaxis":1,"zaxis":-2},{"color":"df7f01","controller":{"active":false,"controllers":null,"id":2453,"joints":null,"mode":0},"pos":{"x":4,"y":7,"z":3},"shapeId":"9f0f56e8-2c31-4d83-996c-d00a9b296c3f","xaxis":1,"zaxis":-2},{"color":"df7f01","controller":{"active":false,"controllers":null,"id":2454,"joints":null,"mode":0},"pos":{"x":4,"y":8,"z":3},"shapeId":"9f0f56e8-2c31-4d83-996c-d00a9b296c3f","xaxis":1,"zaxis":-2},{"color":"df7f01","controller":{"active":false,"controllers":null,"id":2455,"joints":null,"mode":0},"pos":{"x":4,"y":9,"z":3},"shapeId":"9f0f56e8-2c31-4d83-996c-d00a9b296c3f","xaxis":1,"zaxis":-2},{"color":"df7f01","controller":{"active":false,"controllers":null,"id":2456,"joints":null,"mode":0},"pos":{"x":4,"y":11,"z":3},"shapeId":"9f0f56e8-2c31-4d83-996c-d00a9b296c3f","xaxis":1,"zaxis":-2},{"color":"df7f01","controller":{"active":false,"controllers":null,"id":2457,"joints":null,"mode":0},"pos":{"x":4,"y":10,"z":3},"shapeId":"9f0f56e8-2c31-4d83-996c-d00a9b296c3f","xaxis":1,"zaxis":-2},{"color":"df7f01","controller":{"active":false,"controllers":null,"id":2458,"joints":null,"mode":0},"pos":{"x":4,"y":12,"z":3},"shapeId":"9f0f56e8-2c31-4d83-996c-d00a9b296c3f","xaxis":1,"zaxis":-2},{"color":"df7f01","controller":{"active":false,"controllers":null,"id":2459,"joints":null,"mode":0},"pos":{"x":4,"y":13,"z":3},"shapeId":"9f0f56e8-2c31-4d83-996c-d00a9b296c3f","xaxis":1,"zaxis":-2},{"color":"df7f01","controller":{"active":false,"controllers":null,"id":2460,"joints":null,"mode":0},"pos":{"x":4,"y":16,"z":3},"shapeId":"9f0f56e8-2c31-4d83-996c-d00a9b296c3f","xaxis":1,"zaxis":-2},{"color":"df7f01","controller":{"active":false,"controllers":null,"id":2461,"joints":null,"mode":0},"pos":{"x":4,"y":15,"z":3},"shapeId":"9f0f56e8-2c31-4d83-996c-d00a9b296c3f","xaxis":1,"zaxis":-2},{"color":"df7f01","controller":{"active":false,"controllers":null,"id":2462,"joints":null,"mode":0},"pos":{"x":4,"y":14,"z":3},"shapeId":"9f0f56e8-2c31-4d83-996c-d00a9b296c3f","xaxis":1,"zaxis":-2},{"color":"df7f01","controller":{"active":false,"controllers":[{"id":2499},{"id":2489}],"id":2507,"joints":null,"mode":0},"pos":{"x":4,"y":8,"z":-1},"shapeId":"9f0f56e8-2c31-4d83-996c-d00a9b296c3f","xaxis":2,"zaxis":-3},{"color":"df7f01","controller":{"active":false,"controllers":[{"id":2502},{"id":2486}],"id":2511,"joints":null,"mode":0},"pos":{"x":4,"y":11,"z":-1},"shapeId":"9f0f56e8-2c31-4d83-996c-d00a9b296c3f","xaxis":2,"zaxis":-3},{"bounds":{"x":1,"y":16,"z":1},"color":"675f51","pos":{"x":4,"y":0,"z":2},"shapeId":"8aedf6c2-94e1-4506-89d4-a0227c552f1e","xaxis":1,"zaxis":3},{"color":"df7f01","controller":{"active":false,"controllers":[{"id":2498},{"id":2490}],"id":2508,"joints":null,"mode":0},"pos":{"x":4,"y":7,"z":-1},"shapeId":"9f0f56e8-2c31-4d83-996c-d00a9b296c3f","xaxis":2,"zaxis":-3},{"color":"df7f01","controller":{"active":false,"controllers":[{"id":2500},{"id":2488}],"id":2509,"joints":null,"mode":0},"pos":{"x":4,"y":9,"z":-1},"shapeId":"9f0f56e8-2c31-4d83-996c-d00a9b296c3f","xaxis":2,"zaxis":-3}]}],"version":3}
