{"bodies":[{"childs":[{"bounds":{"x":1,"y":1,"z":2},"color":"9b683a","joints":[{"id":195},{"id":221}],"pos":{"x":25,"y":-1,"z":1},"shapeId":"df953d9c-234f-4ac2-af5e-f0490b223e71","xaxis":1,"zaxis":3}]},{"childs":[{"color":"df7f00","joints":[{"id":230}],"pos":{"x":18,"y":0,"z":4},"shapeId":"db66f0b1-0c50-4b74-bdc7-771374204b1f","xaxis":-3,"zaxis":2}]},{"childs":[{"bounds":{"x":1,"y":1,"z":1},"color":"9b683a","joints":[{"id":212},{"id":211}],"pos":{"x":16,"y":-1,"z":7},"shapeId":"df953d9c-234f-4ac2-af5e-f0490b223e71","xaxis":1,"zaxis":3}]},{"childs":[{"bounds":{"x":1,"y":1,"z":1},"color":"9b683a","joints":[{"id":217},{"id":216}],"pos":{"x":16,"y":-9,"z":7},"shapeId":"df953d9c-234f-4ac2-af5e-f0490b223e71","xaxis":1,"zaxis":3}]},{"childs":[{"bounds":{"x":1,"y":1,"z":1},"color":"9b683a","joints":[{"id":213},{"id":212}],"pos":{"x":16,"y":-1,"z":6},"shapeId":"df953d9c-234f-4ac2-af5e-f0490b223e71","xaxis":1,"zaxis":3}]},{"childs":[{"color":"df7f00","controller":{"controllers":null,"id":413,"joints":null,"playMode":0,"timePerFrame":1.0},"pos":{"x":27,"y":-4,"z":3},"shapeId":"12862001-666c-4bdd-8326-a1f43610d28b","xaxis":-1,"zaxis":2},{"color":"df7f00","controller":{"controllers":null,"id":412,"joints":[{"endAngle":45,"frames":[{"targetAngle":0},{"targetAngle":45},{"targetAngle":0},{"targetAngle":0},{"targetAngle":0},{"targetAngle":0},{"targetAngle":0},{"targetAngle":0},{"targetAngle":0},{"targetAngle":0},{"targetAngle":0}],"id":212,"index":0,"reverse":true,"startAngle":0}],"playMode":0,"timePerFrame":1.0},"pos":{"x":27,"y":-6,"z":3},"shapeId":"12862001-666c-4bdd-8326-a1f43610d28b","xaxis":-1,"zaxis":2},{"color":"df7f00","controller":{"controllers":null,"id":411,"joints":[{"endAngle":-45,"frames":[{"targetAngle":0},{"targetAngle":-45},{"targetAngle":0},{"targetAngle":0},{"targetAngle":0},{"targetAngle":0},{"targetAngle":0},{"targetAngle":0},{"targetAngle":0},{"targetAngle":0},{"targetAngle":0}],"id":217,"index":0,"reverse":true,"startAngle":0}],"playMode":0,"timePerFrame":1.0},"pos":{"x":27,"y":-5,"z":3},"shapeId":"12862001-666c-4bdd-8326-a1f43610d28b","xaxis":-1,"zaxis":2},{"bounds":{"x":1,"y":1,"z":1},"color":"675f51","pos":{"x":24,"y":-7,"z":3},"shapeId":"8aedf6c2-94e1-4506-89d4-a0227c552f1e","xaxis":1,"zaxis":3},{"bounds":{"x":1,"y":1,"z":1},"color":"675f51","pos":{"x":24,"y":-3,"z":3},"shapeId":"8aedf6c2-94e1-4506-89d4-a0227c552f1e","xaxis":1,"zaxis":3},{"color":"df7f00","controller":{"active":false,"controllers":[{"id":413}],"id":407,"joints":null,"mode":0},"pos":{"x":23,"y":-4,"z":4},"shapeId":"9f0f56e8-2c31-4d83-996c-d00a9b296c3f","xaxis":-3,"zaxis":2},{"color":"df7f00","controller":{"active":false,"controllers":[{"id":411}],"id":406,"joints":null,"mode":0},"pos":{"x":22,"y":-5,"z":3},"shapeId":"9f0f56e8-2c31-4d83-996c-d00a9b296c3f","xaxis":1,"zaxis":-2},{"color":"df7f00","controller":{"active":false,"controllers":[{"id":412}],"id":405,"joints":null,"mode":0},"pos":{"x":22,"y":-4,"z":3},"shapeId":"9f0f56e8-2c31-4d83-996c-d00a9b296c3f","xaxis":1,"zaxis":-2},{"color":"df7f00","controller":{"controllers":null,"gear":8,"id":402,"joints":[{"id":228,"reverse":1},{"id":230,"reverse":0}]},"pos":{"x":18,"y":-6,"z":3},"shapeId":"d5e36413-b3c1-4636-8447-3410c352ec7b","xaxis":1,"zaxis":-2},{"color":"df7f00","controller":{"controllers":null,"gear":4,"id":401,"joints":[{"id":225,"reverse":1},{"id":223,"reverse":1}]},"pos":{"x":18,"y":-1,"z":3},"shapeId":"d5e36413-b3c1-4636-8447-3410c352ec7b","xaxis":1,"zaxis":-2},{"bounds":{"x":4,"y":7,"z":1},"color":"9b683a","joints":[{"id":207}],"pos":{"x":15,"y":-8,"z":2},"shapeId":"df953d9c-234f-4ac2-af5e-f0490b223e71","xaxis":1,"zaxis":3},{"bounds":{"x":6,"y":9,"z":1},"color":"9b683a","pos":{"x":19,"y":-9,"z":2},"shapeId":"df953d9c-234f-4ac2-af5e-f0490b223e71","xaxis":1,"zaxis":3},{"bounds":{"x":1,"y":7,"z":1},"color":"9b683a","pos":{"x":25,"y":-8,"z":2},"shapeId":"df953d9c-234f-4ac2-af5e-f0490b223e71","xaxis":1,"zaxis":3},{"bounds":{"x":1,"y":1,"z":4},"color":"9b683a","pos":{"x":26,"y":-8,"z":3},"shapeId":"df953d9c-234f-4ac2-af5e-f0490b223e71","xaxis":1,"zaxis":3},{"bounds":{"x":1,"y":1,"z":1},"color":"9b683a","joints":[{"id":196}],"pos":{"x":26,"y":-9,"z":6},"shapeId":"df953d9c-234f-4ac2-af5e-f0490b223e71","xaxis":1,"zaxis":3},{"bounds":{"x":1,"y":6,"z":1},"color":"9b683a","pos":{"x":26,"y":-8,"z":2},"shapeId":"df953d9c-234f-4ac2-af5e-f0490b223e71","xaxis":1,"zaxis":3},{"bounds":{"x":2,"y":3,"z":1},"color":"9b683a","pos":{"x":27,"y":-6,"z":2},"shapeId":"df953d9c-234f-4ac2-af5e-f0490b223e71","xaxis":1,"zaxis":3},{"color":"df7f00","controller":{"controllers":null,"gear":8,"id":397,"joints":null},"pos":{"x":25,"y":-6,"z":3},"shapeId":"6546c293-a5aa-4442-80d5-a2819f077746","xaxis":-1,"zaxis":2},{"color":"df7f00","controller":{"controllers":[{"id":402},{"id":401}],"id":396,"joints":[{"id":207,"reverse":0}]},"pos":{"x":22,"y":-3,"z":3},"shapeId":"38ee0516-abc5-4e46-9195-c763610d7ec4","xaxis":-2,"zaxis":-1},{"bounds":{"x":1,"y":1,"z":1},"color":"9b683a","pos":{"x":28,"y":-4,"z":3},"shapeId":"df953d9c-234f-4ac2-af5e-f0490b223e71","xaxis":1,"zaxis":3},{"bounds":{"x":1,"y":1,"z":1},"color":"9b683a","pos":{"x":28,"y":-6,"z":3},"shapeId":"df953d9c-234f-4ac2-af5e-f0490b223e71","xaxis":1,"zaxis":3},{"color":"df7f00","controller":{"controllers":null,"id":395,"joints":[{"endAngle":-30,"frames":[{"targetAngle":-30},{"targetAngle":0},{"targetAngle":0},{"targetAngle":0},{"targetAngle":0},{"targetAngle":0},{"targetAngle":0},{"targetAngle":0},{"targetAngle":0},{"targetAngle":0},{"targetAngle":0}],"id":216,"index":2,"reverse":true,"startAngle":-30},{"endAngle":30,"frames":[{"targetAngle":30},{"targetAngle":0},{"targetAngle":0},{"targetAngle":0},{"targetAngle":0},{"targetAngle":0},{"targetAngle":0},{"targetAngle":0},{"targetAngle":0},{"targetAngle":0},{"targetAngle":0}],"id":194,"index":7,"reverse":false,"startAngle":30},{"endAngle":-30,"frames":[{"targetAngle":-30},{"targetAngle":0},{"targetAngle":0},{"targetAngle":0},{"targetAngle":0},{"targetAngle":0},{"targetAngle":0},{"targetAngle":0},{"targetAngle":0},{"targetAngle":0},{"targetAngle":0}],"id":196,"index":0,"reverse":false,"startAngle":-30},{"endAngle":30,"frames":[{"targetAngle":30},{"targetAngle":0},{"targetAngle":0},{"targetAngle":0},{"targetAngle":0},{"targetAngle":0},{"targetAngle":0},{"targetAngle":0},{"targetAngle":0},{"targetAngle":0},{"targetAngle":0}],"id":211,"index":1,"reverse":true,"startAngle":30},{"endAngle":-30,"frames":[{"targetAngle":-30},{"targetAngle":0},{"targetAngle":0},{"targetAngle":0},{"targetAngle":0},{"targetAngle":0},{"targetAngle":0},{"targetAngle":0},{"targetAngle":0},{"targetAngle":0},{"targetAngle":0}],"id":221,"index":6,"reverse":true,"startAngle":-30},{"endAngle":-30,"frames":[{"targetAngle":-30},{"targetAngle":0},{"targetAngle":0},{"targetAngle":0},{"targetAngle":0},{"targetAngle":0},{"targetAngle":0},{"targetAngle":0},{"targetAngle":0},{"targetAngle":0},{"targetAngle":0}],"id":224,"index":3,"reverse":false,"startAngle":-30},{"endAngle":-30,"frames":[{"targetAngle":-30},{"targetAngle":0},{"targetAngle":0},{"targetAngle":0},{"targetAngle":0},{"targetAngle":0},{"targetAngle":0},{"targetAngle":0},{"targetAngle":0},{"targetAngle":0},{"targetAngle":0}],"id":226,"index":4,"reverse":true,"startAngle":-30},{"endAngle":-30,"frames":[{"targetAngle":-30},{"targetAngle":0},{"targetAngle":0},{"targetAngle":0},{"targetAngle":0},{"targetAngle":0},{"targetAngle":0},{"targetAngle":0},{"targetAngle":0},{"targetAngle":0},{"targetAngle":0}],"id":229,"index":5,"reverse":false,"startAngle":-30}],"playMode":0,"timePerFrame":1.0},"pos":{"x":23,"y":-4,"z":5},"shapeId":"12862001-666c-4bdd-8326-a1f43610d28b","xaxis":1,"zaxis":-2},{"bounds":{"x":1,"y":1,"z":1},"color":"9b683a","joints":[{"id":194}],"pos":{"x":26,"y":-1,"z":6},"shapeId":"df953d9c-234f-4ac2-af5e-f0490b223e71","xaxis":1,"zaxis":3},{"bounds":{"x":1,"y":1,"z":5},"color":"9b683a","pos":{"x":26,"y":-2,"z":2},"shapeId":"df953d9c-234f-4ac2-af5e-f0490b223e71","xaxis":1,"zaxis":3}]},{"childs":[{"bounds":{"x":1,"y":1,"z":1},"color":"9b683a","joints":[{"id":228},{"id":226}],"pos":{"x":15,"y":-9,"z":1},"shapeId":"df953d9c-234f-4ac2-af5e-f0490b223e71","xaxis":1,"zaxis":3}]},{"childs":[{"bounds":{"x":1,"y":1,"z":1},"color":"9b683a","joints":[{"id":218},{"id":217}],"pos":{"x":16,"y":-9,"z":6},"shapeId":"df953d9c-234f-4ac2-af5e-f0490b223e71","xaxis":1,"zaxis":3}]},{"childs":[{"bounds":{"x":1,"y":1,"z":1},"color":"9b683a","joints":[{"id":216}],"pos":{"x":15,"y":-9,"z":7},"shapeId":"df953d9c-234f-4ac2-af5e-f0490b223e71","xaxis":1,"zaxis":3},{"bounds":{"x":1,"y":1,"z":4},"color":"9b683a","pos":{"x":15,"y":-8,"z":4},"shapeId":"df953d9c-234f-4ac2-af5e-f0490b223e71","xaxis":1,"zaxis":3},{"bounds":{"x":1,"y":7,"z":1},"color":"9b683a","joints":[{"id":207}],"pos":{"x":15,"y":-8,"z":3},"shapeId":"df953d9c-234f-4ac2-af5e-f0490b223e71","xaxis":1,"zaxis":3},{"bounds":{"x":1,"y":1,"z":1},"color":"9b683a","joints":[{"id":211}],"pos":{"x":15,"y":-1,"z":7},"shapeId":"df953d9c-234f-4ac2-af5e-f0490b223e71","xaxis":1,"zaxis":3},{"bounds":{"x":1,"y":1,"z":4},"color":"9b683a","pos":{"x":15,"y":-2,"z":4},"shapeId":"df953d9c-234f-4ac2-af5e-f0490b223e71","xaxis":1,"zaxis":3}]},{"childs":[{"bounds":{"x":1,"y":1,"z":2},"color":"9b683a","joints":[{"id":229},{"id":213}],"pos":{"x":16,"y":-1,"z":1},"shapeId":"df953d9c-234f-4ac2-af5e-f0490b223e71","xaxis":1,"zaxis":3}]},{"childs":[{"bounds":{"x":1,"y":1,"z":1},"color":"9b683a","joints":[{"id":221},{"id":223}],"pos":{"x":26,"y":-1,"z":1},"shapeId":"df953d9c-234f-4ac2-af5e-f0490b223e71","xaxis":1,"zaxis":3}]},{"childs":[{"color":"df7f00","joints":[{"id":223}],"pos":{"x":29,"y":0,"z":4},"shapeId":"db66f0b1-0c50-4b74-bdc7-771374204b1f","xaxis":-3,"zaxis":2}]},{"childs":[{"bounds":{"x":1,"y":1,"z":1},"color":"9b683a","joints":[{"id":197},{"id":196}],"pos":{"x":25,"y":-9,"z":6},"shapeId":"df953d9c-234f-4ac2-af5e-f0490b223e71","xaxis":1,"zaxis":3}]},{"childs":[{"bounds":{"x":1,"y":1,"z":1},"color":"9b683a","joints":[{"id":229},{"id":230}],"pos":{"x":15,"y":-1,"z":1},"shapeId":"df953d9c-234f-4ac2-af5e-f0490b223e71","xaxis":1,"zaxis":3}]},{"childs":[{"bounds":{"x":1,"y":1,"z":1},"color":"9b683a","joints":[{"id":225},{"id":224}],"pos":{"x":26,"y":-9,"z":1},"shapeId":"df953d9c-234f-4ac2-af5e-f0490b223e71","xaxis":1,"zaxis":3}]},{"childs":[{"color":"df7f00","joints":[{"id":225}],"pos":{"x":24,"y":-9,"z":4},"shapeId":"db66f0b1-0c50-4b74-bdc7-771374204b1f","xaxis":-3,"zaxis":-2}]},{"childs":[{"bounds":{"x":1,"y":1,"z":1},"color":"9b683a","joints":[{"id":195},{"id":194}],"pos":{"x":25,"y":-1,"z":6},"shapeId":"df953d9c-234f-4ac2-af5e-f0490b223e71","xaxis":1,"zaxis":3}]},{"childs":[{"bounds":{"x":1,"y":1,"z":2},"color":"9b683a","joints":[{"id":197},{"id":224}],"pos":{"x":25,"y":-9,"z":1},"shapeId":"df953d9c-234f-4ac2-af5e-f0490b223e71","xaxis":1,"zaxis":3}]},{"childs":[{"bounds":{"x":1,"y":1,"z":2},"color":"9b683a","joints":[{"id":226},{"id":218}],"pos":{"x":16,"y":-9,"z":1},"shapeId":"df953d9c-234f-4ac2-af5e-f0490b223e71","xaxis":1,"zaxis":3}]},{"childs":[{"color":"df7f00","joints":[{"id":228}],"pos":{"x":13,"y":-9,"z":4},"shapeId":"db66f0b1-0c50-4b74-bdc7-771374204b1f","xaxis":-3,"zaxis":-2}]}],"joints":[{"childA":27,"childB":43,"color":"df7f00","id":194,"posA":{"x":25,"y":-1,"z":6},"posB":{"x":25,"y":-1,"z":6},"shapeId":"4a1b886b-913e-4aad-b5b6-6e41b0db23a6","xaxisA":2,"xaxisB":2,"zaxisA":-1,"zaxisB":-1},{"childA":43,"childB":0,"color":"df7f00","controller":{"controllers":null,"id":393,"joints":null,"stiffnessLevel":4},"id":195,"posA":{"x":25,"y":-1,"z":5},"posB":{"x":25,"y":-1,"z":2},"shapeId":"a481138b-fae9-47c9-9bc2-91b6d2e2bf52","xaxisA":1,"xaxisB":1,"zaxisA":-3,"zaxisB":-3},{"childA":19,"childB":39,"color":"df7f00","id":196,"posA":{"x":25,"y":-9,"z":6},"posB":{"x":25,"y":-9,"z":6},"shapeId":"4a1b886b-913e-4aad-b5b6-6e41b0db23a6","xaxisA":2,"xaxisB":2,"zaxisA":-1,"zaxisB":-1},{"childA":39,"childB":44,"color":"df7f00","controller":{"controllers":null,"id":394,"joints":null,"stiffnessLevel":4},"id":197,"posA":{"x":25,"y":-9,"z":5},"posB":{"x":25,"y":-9,"z":2},"shapeId":"a481138b-fae9-47c9-9bc2-91b6d2e2bf52","xaxisA":1,"xaxisB":1,"zaxisA":-3,"zaxisB":-3},{"childA":15,"childB":33,"color":"df7f00","id":207,"posA":{"x":15,"y":-5,"z":3},"posB":{"x":15,"y":-5,"z":3},"shapeId":"4a1b886b-913e-4aad-b5b6-6e41b0db23a6","xaxisA":1,"xaxisB":1,"zaxisA":3,"zaxisB":3},{"childA":34,"childB":2,"color":"df7f00","id":211,"posA":{"x":16,"y":-1,"z":7},"posB":{"x":16,"y":-1,"z":7},"shapeId":"4a1b886b-913e-4aad-b5b6-6e41b0db23a6","xaxisA":2,"xaxisB":2,"zaxisA":1,"zaxisB":1},{"childA":2,"childB":4,"color":"df7f00","id":212,"posA":{"x":16,"y":-1,"z":6},"posB":{"x":16,"y":-1,"z":6},"shapeId":"4a1b886b-913e-4aad-b5b6-6e41b0db23a6","xaxisA":1,"xaxisB":1,"zaxisA":-3,"zaxisB":-3},{"childA":4,"childB":36,"color":"df7f00","controller":{"controllers":null,"id":399,"joints":null,"stiffnessLevel":10},"id":213,"posA":{"x":16,"y":-1,"z":5},"posB":{"x":16,"y":-1,"z":2},"shapeId":"a481138b-fae9-47c9-9bc2-91b6d2e2bf52","xaxisA":1,"xaxisB":1,"zaxisA":-3,"zaxisB":-3},{"childA":31,"childB":3,"color":"df7f00","id":216,"posA":{"x":16,"y":-9,"z":7},"posB":{"x":16,"y":-9,"z":7},"shapeId":"4a1b886b-913e-4aad-b5b6-6e41b0db23a6","xaxisA":2,"xaxisB":2,"zaxisA":1,"zaxisB":1},{"childA":3,"childB":30,"color":"df7f00","id":217,"posA":{"x":16,"y":-9,"z":6},"posB":{"x":16,"y":-9,"z":6},"shapeId":"4a1b886b-913e-4aad-b5b6-6e41b0db23a6","xaxisA":1,"xaxisB":1,"zaxisA":-3,"zaxisB":-3},{"childA":30,"childB":45,"color":"df7f00","controller":{"controllers":null,"id":400,"joints":null,"stiffnessLevel":10},"id":218,"posA":{"x":16,"y":-9,"z":5},"posB":{"x":16,"y":-9,"z":2},"shapeId":"a481138b-fae9-47c9-9bc2-91b6d2e2bf52","xaxisA":1,"xaxisB":1,"zaxisA":-3,"zaxisB":-3},{"childA":0,"childB":37,"color":"df7f00","id":221,"posA":{"x":26,"y":-1,"z":1},"posB":{"x":26,"y":-1,"z":1},"shapeId":"4a1b886b-913e-4aad-b5b6-6e41b0db23a6","xaxisA":2,"xaxisB":2,"zaxisA":1,"zaxisB":1},{"childA":37,"childB":38,"color":"df7f00","id":223,"posA":{"x":26,"y":0,"z":1},"posB":{"x":26,"y":0,"z":1},"shapeId":"4a1b886b-913e-4aad-b5b6-6e41b0db23a6","xaxisA":1,"xaxisB":1,"zaxisA":2,"zaxisB":2},{"childA":44,"childB":41,"color":"df7f00","id":224,"posA":{"x":26,"y":-9,"z":1},"posB":{"x":26,"y":-9,"z":1},"shapeId":"4a1b886b-913e-4aad-b5b6-6e41b0db23a6","xaxisA":2,"xaxisB":2,"zaxisA":1,"zaxisB":1},{"childA":41,"childB":42,"color":"df7f00","id":225,"posA":{"x":26,"y":-10,"z":1},"posB":{"x":26,"y":-10,"z":1},"shapeId":"4a1b886b-913e-4aad-b5b6-6e41b0db23a6","xaxisA":1,"xaxisB":1,"zaxisA":-2,"zaxisB":-2},{"childA":45,"childB":29,"color":"df7f00","id":226,"posA":{"x":15,"y":-9,"z":1},"posB":{"x":15,"y":-9,"z":1},"shapeId":"4a1b886b-913e-4aad-b5b6-6e41b0db23a6","xaxisA":2,"xaxisB":2,"zaxisA":-1,"zaxisB":-1},{"childA":29,"childB":46,"color":"df7f00","id":228,"posA":{"x":15,"y":-10,"z":1},"posB":{"x":15,"y":-10,"z":1},"shapeId":"4a1b886b-913e-4aad-b5b6-6e41b0db23a6","xaxisA":1,"xaxisB":1,"zaxisA":-2,"zaxisB":-2},{"childA":36,"childB":40,"color":"df7f00","id":229,"posA":{"x":15,"y":-1,"z":1},"posB":{"x":15,"y":-1,"z":1},"shapeId":"4a1b886b-913e-4aad-b5b6-6e41b0db23a6","xaxisA":2,"xaxisB":2,"zaxisA":-1,"zaxisB":-1},{"childA":40,"childB":1,"color":"df7f00","id":230,"posA":{"x":15,"y":0,"z":1},"posB":{"x":15,"y":0,"z":1},"shapeId":"4a1b886b-913e-4aad-b5b6-6e41b0db23a6","xaxisA":1,"xaxisB":1,"zaxisA":2,"zaxisB":2}],"version":2}
